[{"arguments":["clang","-Wno-documentation-unknown-command","-Wno-unknown-warning-option","-Wno-unknown-pragmas","-nostdinc","-nostdinc++","-std=gnu++1z","-Wall","-Wextra","-Wextra","-fexceptions","-mthreads","-fsyntax-only","-m64","--target=x86_64-w64-mingw32","-DUNICODE","-D_UNICODE","-DWIN32","-DMINGW_HAS_SECURE_API","-DQT_NO_DEBUG","-DQT_WIDGETS_LIB","-DQT_GUI_LIB","-DQT_NETWORK_LIB","-DQT_CORE_LIB","-DQT_NEEDS_QMAIN","-DQ_CREATOR_RUN","-DQT_ANNOTATE_FUNCTION(x)=__attribute__((annotate(#x)))","-IE:\\QT\\Tools\\QtCreator\\share\\qtcreator\\cplusplus\\wrappedMingwHeaders","-IE:\\QT\\Tools\\QtCreator\\share\\qtcreator\\cplusplus\\wrappedQtHeaders","-IE:\\QT\\Tools\\QtCreator\\share\\qtcreator\\cplusplus\\wrappedQtHeaders\\QtCore","-ID:\\SkullKing_Game\\SkullKing","-IE:\\QT\\6.7.2\\mingw_64\\include","-IE:\\QT\\6.7.2\\mingw_64\\include\\QtWidgets","-IE:\\QT\\6.7.2\\mingw_64\\include\\QtGui","-IE:\\QT\\6.7.2\\mingw_64\\include\\QtNetwork","-IE:\\QT\\6.7.2\\mingw_64\\include\\QtCore","-ID:\\SkullKing_Game\\SkullKing\\build\\Desktop_Qt_6_7_2_MinGW_64_bit-Release\\release","-ID:\\SkullKing_Game\\SkullKing\\build\\Desktop_Qt_6_7_2_MinGW_64_bit-Release","-IE:\\QT\\6.7.2\\mingw_64\\mkspecs\\win32-g++","-isystem","E:\\QT\\Tools\\mingw1120_64\\lib\\gcc\\x86_64-w64-mingw32\\11.2.0\\include\\c++","-isystem","E:\\QT\\Tools\\mingw1120_64\\lib\\gcc\\x86_64-w64-mingw32\\11.2.0\\include\\c++\\x86_64-w64-mingw32","-isystem","E:\\QT\\Tools\\mingw1120_64\\lib\\gcc\\x86_64-w64-mingw32\\11.2.0\\include\\c++\\backward","-isystem","E:\\QT\\Tools\\QtCreator\\bin\\clang\\lib\\clang\\17\\include","-isystem","E:\\QT\\Tools\\mingw1120_64\\x86_64-w64-mingw32\\include","-fmessage-length=0","-fdiagnostics-show-note-include-stack","-fretain-comments-from-system-headers","-fmacro-backtrace-limit=0","-ferror-limit=1000","-x","c++","D:\\SkullKing_Game\\SkullKing\\cards.cpp"],"directory":"D:/SkullKing_Game/SkullKing/build/Desktop_Qt_6_7_2_MinGW_64_bit-Release/.qtc_clangd","file":"D:/SkullKing_Game/SkullKing/cards.cpp"},{"arguments":["clang","-Wno-documentation-unknown-command","-Wno-unknown-warning-option","-Wno-unknown-pragmas","-nostdinc","-nostdinc++","-std=gnu++1z","-Wall","-Wextra","-Wextra","-fexceptions","-mthreads","-fsyntax-only","-m64","--target=x86_64-w64-mingw32","-DUNICODE","-D_UNICODE","-DWIN32","-DMINGW_HAS_SECURE_API","-DQT_NO_DEBUG","-DQT_WIDGETS_LIB","-DQT_GUI_LIB","-DQT_NETWORK_LIB","-DQT_CORE_LIB","-DQT_NEEDS_QMAIN","-DQ_CREATOR_RUN","-DQT_ANNOTATE_FUNCTION(x)=__attribute__((annotate(#x)))","-IE:\\QT\\Tools\\QtCreator\\share\\qtcreator\\cplusplus\\wrappedMingwHeaders","-IE:\\QT\\Tools\\QtCreator\\share\\qtcreator\\cplusplus\\wrappedQtHeaders","-IE:\\QT\\Tools\\QtCreator\\share\\qtcreator\\cplusplus\\wrappedQtHeaders\\QtCore","-ID:\\SkullKing_Game\\SkullKing","-IE:\\QT\\6.7.2\\mingw_64\\include","-IE:\\QT\\6.7.2\\mingw_64\\include\\QtWidgets","-IE:\\QT\\6.7.2\\mingw_64\\include\\QtGui","-IE:\\QT\\6.7.2\\mingw_64\\include\\QtNetwork","-IE:\\QT\\6.7.2\\mingw_64\\include\\QtCore","-ID:\\SkullKing_Game\\SkullKing\\build\\Desktop_Qt_6_7_2_MinGW_64_bit-Release\\release","-ID:\\SkullKing_Game\\SkullKing\\build\\Desktop_Qt_6_7_2_MinGW_64_bit-Release","-IE:\\QT\\6.7.2\\mingw_64\\mkspecs\\win32-g++","-isystem","E:\\QT\\Tools\\mingw1120_64\\lib\\gcc\\x86_64-w64-mingw32\\11.2.0\\include\\c++","-isystem","E:\\QT\\Tools\\mingw1120_64\\lib\\gcc\\x86_64-w64-mingw32\\11.2.0\\include\\c++\\x86_64-w64-mingw32","-isystem","E:\\QT\\Tools\\mingw1120_64\\lib\\gcc\\x86_64-w64-mingw32\\11.2.0\\include\\c++\\backward","-isystem","E:\\QT\\Tools\\QtCreator\\bin\\clang\\lib\\clang\\17\\include","-isystem","E:\\QT\\Tools\\mingw1120_64\\x86_64-w64-mingw32\\include","-fmessage-length=0","-fdiagnostics-show-note-include-stack","-fretain-comments-from-system-headers","-fmacro-backtrace-limit=0","-ferror-limit=1000","-x","c++","D:\\SkullKing_Game\\SkullKing\\changeinformation.cpp"],"directory":"D:/SkullKing_Game/SkullKing/build/Desktop_Qt_6_7_2_MinGW_64_bit-Release/.qtc_clangd","file":"D:/SkullKing_Game/SkullKing/changeinformation.cpp"},{"arguments":["clang","-Wno-documentation-unknown-command","-Wno-unknown-warning-option","-Wno-unknown-pragmas","-nostdinc","-nostdinc++","-std=gnu++1z","-Wall","-Wextra","-Wextra","-fexceptions","-mthreads","-fsyntax-only","-m64","--target=x86_64-w64-mingw32","-DUNICODE","-D_UNICODE","-DWIN32","-DMINGW_HAS_SECURE_API","-DQT_NO_DEBUG","-DQT_WIDGETS_LIB","-DQT_GUI_LIB","-DQT_NETWORK_LIB","-DQT_CORE_LIB","-DQT_NEEDS_QMAIN","-DQ_CREATOR_RUN","-DQT_ANNOTATE_FUNCTION(x)=__attribute__((annotate(#x)))","-IE:\\QT\\Tools\\QtCreator\\share\\qtcreator\\cplusplus\\wrappedMingwHeaders","-IE:\\QT\\Tools\\QtCreator\\share\\qtcreator\\cplusplus\\wrappedQtHeaders","-IE:\\QT\\Tools\\QtCreator\\share\\qtcreator\\cplusplus\\wrappedQtHeaders\\QtCore","-ID:\\SkullKing_Game\\SkullKing","-IE:\\QT\\6.7.2\\mingw_64\\include","-IE:\\QT\\6.7.2\\mingw_64\\include\\QtWidgets","-IE:\\QT\\6.7.2\\mingw_64\\include\\QtGui","-IE:\\QT\\6.7.2\\mingw_64\\include\\QtNetwork","-IE:\\QT\\6.7.2\\mingw_64\\include\\QtCore","-ID:\\SkullKing_Game\\SkullKing\\build\\Desktop_Qt_6_7_2_MinGW_64_bit-Release\\release","-ID:\\SkullKing_Game\\SkullKing\\build\\Desktop_Qt_6_7_2_MinGW_64_bit-Release","-IE:\\QT\\6.7.2\\mingw_64\\mkspecs\\win32-g++","-isystem","E:\\QT\\Tools\\mingw1120_64\\lib\\gcc\\x86_64-w64-mingw32\\11.2.0\\include\\c++","-isystem","E:\\QT\\Tools\\mingw1120_64\\lib\\gcc\\x86_64-w64-mingw32\\11.2.0\\include\\c++\\x86_64-w64-mingw32","-isystem","E:\\QT\\Tools\\mingw1120_64\\lib\\gcc\\x86_64-w64-mingw32\\11.2.0\\include\\c++\\backward","-isystem","E:\\QT\\Tools\\QtCreator\\bin\\clang\\lib\\clang\\17\\include","-isystem","E:\\QT\\Tools\\mingw1120_64\\x86_64-w64-mingw32\\include","-fmessage-length=0","-fdiagnostics-show-note-include-stack","-fretain-comments-from-system-headers","-fmacro-backtrace-limit=0","-ferror-limit=1000","-x","c++","D:\\SkullKing_Game\\SkullKing\\client.cpp"],"directory":"D:/SkullKing_Game/SkullKing/build/Desktop_Qt_6_7_2_MinGW_64_bit-Release/.qtc_clangd","file":"D:/SkullKing_Game/SkullKing/client.cpp"},{"arguments":["clang","-Wno-documentation-unknown-command","-Wno-unknown-warning-option","-Wno-unknown-pragmas","-nostdinc","-nostdinc++","-std=gnu++1z","-Wall","-Wextra","-Wextra","-fexceptions","-mthreads","-fsyntax-only","-m64","--target=x86_64-w64-mingw32","-DUNICODE","-D_UNICODE","-DWIN32","-DMINGW_HAS_SECURE_API","-DQT_NO_DEBUG","-DQT_WIDGETS_LIB","-DQT_GUI_LIB","-DQT_NETWORK_LIB","-DQT_CORE_LIB","-DQT_NEEDS_QMAIN","-DQ_CREATOR_RUN","-DQT_ANNOTATE_FUNCTION(x)=__attribute__((annotate(#x)))","-IE:\\QT\\Tools\\QtCreator\\share\\qtcreator\\cplusplus\\wrappedMingwHeaders","-IE:\\QT\\Tools\\QtCreator\\share\\qtcreator\\cplusplus\\wrappedQtHeaders","-IE:\\QT\\Tools\\QtCreator\\share\\qtcreator\\cplusplus\\wrappedQtHeaders\\QtCore","-ID:\\SkullKing_Game\\SkullKing","-IE:\\QT\\6.7.2\\mingw_64\\include","-IE:\\QT\\6.7.2\\mingw_64\\include\\QtWidgets","-IE:\\QT\\6.7.2\\mingw_64\\include\\QtGui","-IE:\\QT\\6.7.2\\mingw_64\\include\\QtNetwork","-IE:\\QT\\6.7.2\\mingw_64\\include\\QtCore","-ID:\\SkullKing_Game\\SkullKing\\build\\Desktop_Qt_6_7_2_MinGW_64_bit-Release\\release","-ID:\\SkullKing_Game\\SkullKing\\build\\Desktop_Qt_6_7_2_MinGW_64_bit-Release","-IE:\\QT\\6.7.2\\mingw_64\\mkspecs\\win32-g++","-isystem","E:\\QT\\Tools\\mingw1120_64\\lib\\gcc\\x86_64-w64-mingw32\\11.2.0\\include\\c++","-isystem","E:\\QT\\Tools\\mingw1120_64\\lib\\gcc\\x86_64-w64-mingw32\\11.2.0\\include\\c++\\x86_64-w64-mingw32","-isystem","E:\\QT\\Tools\\mingw1120_64\\lib\\gcc\\x86_64-w64-mingw32\\11.2.0\\include\\c++\\backward","-isystem","E:\\QT\\Tools\\QtCreator\\bin\\clang\\lib\\clang\\17\\include","-isystem","E:\\QT\\Tools\\mingw1120_64\\x86_64-w64-mingw32\\include","-fmessage-length=0","-fdiagnostics-show-note-include-stack","-fretain-comments-from-system-headers","-fmacro-backtrace-limit=0","-ferror-limit=1000","-x","c++","D:\\SkullKing_Game\\SkullKing\\clientorserver.cpp"],"directory":"D:/SkullKing_Game/SkullKing/build/Desktop_Qt_6_7_2_MinGW_64_bit-Release/.qtc_clangd","file":"D:/SkullKing_Game/SkullKing/clientorserver.cpp"},{"arguments":["clang","-Wno-documentation-unknown-command","-Wno-unknown-warning-option","-Wno-unknown-pragmas","-nostdinc","-nostdinc++","-std=gnu++1z","-Wall","-Wextra","-Wextra","-fexceptions","-mthreads","-fsyntax-only","-m64","--target=x86_64-w64-mingw32","-DUNICODE","-D_UNICODE","-DWIN32","-DMINGW_HAS_SECURE_API","-DQT_NO_DEBUG","-DQT_WIDGETS_LIB","-DQT_GUI_LIB","-DQT_NETWORK_LIB","-DQT_CORE_LIB","-DQT_NEEDS_QMAIN","-DQ_CREATOR_RUN","-DQT_ANNOTATE_FUNCTION(x)=__attribute__((annotate(#x)))","-IE:\\QT\\Tools\\QtCreator\\share\\qtcreator\\cplusplus\\wrappedMingwHeaders","-IE:\\QT\\Tools\\QtCreator\\share\\qtcreator\\cplusplus\\wrappedQtHeaders","-IE:\\QT\\Tools\\QtCreator\\share\\qtcreator\\cplusplus\\wrappedQtHeaders\\QtCore","-ID:\\SkullKing_Game\\SkullKing","-IE:\\QT\\6.7.2\\mingw_64\\include","-IE:\\QT\\6.7.2\\mingw_64\\include\\QtWidgets","-IE:\\QT\\6.7.2\\mingw_64\\include\\QtGui","-IE:\\QT\\6.7.2\\mingw_64\\include\\QtNetwork","-IE:\\QT\\6.7.2\\mingw_64\\include\\QtCore","-ID:\\SkullKing_Game\\SkullKing\\build\\Desktop_Qt_6_7_2_MinGW_64_bit-Release\\release","-ID:\\SkullKing_Game\\SkullKing\\build\\Desktop_Qt_6_7_2_MinGW_64_bit-Release","-IE:\\QT\\6.7.2\\mingw_64\\mkspecs\\win32-g++","-isystem","E:\\QT\\Tools\\mingw1120_64\\lib\\gcc\\x86_64-w64-mingw32\\11.2.0\\include\\c++","-isystem","E:\\QT\\Tools\\mingw1120_64\\lib\\gcc\\x86_64-w64-mingw32\\11.2.0\\include\\c++\\x86_64-w64-mingw32","-isystem","E:\\QT\\Tools\\mingw1120_64\\lib\\gcc\\x86_64-w64-mingw32\\11.2.0\\include\\c++\\backward","-isystem","E:\\QT\\Tools\\QtCreator\\bin\\clang\\lib\\clang\\17\\include","-isystem","E:\\QT\\Tools\\mingw1120_64\\x86_64-w64-mingw32\\include","-fmessage-length=0","-fdiagnostics-show-note-include-stack","-fretain-comments-from-system-headers","-fmacro-backtrace-limit=0","-ferror-limit=1000","-x","c++","D:\\SkullKing_Game\\SkullKing\\common.cpp"],"directory":"D:/SkullKing_Game/SkullKing/build/Desktop_Qt_6_7_2_MinGW_64_bit-Release/.qtc_clangd","file":"D:/SkullKing_Game/SkullKing/common.cpp"},{"arguments":["clang","-Wno-documentation-unknown-command","-Wno-unknown-warning-option","-Wno-unknown-pragmas","-nostdinc","-nostdinc++","-std=gnu++1z","-Wall","-Wextra","-Wextra","-fexceptions","-mthreads","-fsyntax-only","-m64","--target=x86_64-w64-mingw32","-DUNICODE","-D_UNICODE","-DWIN32","-DMINGW_HAS_SECURE_API","-DQT_NO_DEBUG","-DQT_WIDGETS_LIB","-DQT_GUI_LIB","-DQT_NETWORK_LIB","-DQT_CORE_LIB","-DQT_NEEDS_QMAIN","-DQ_CREATOR_RUN","-DQT_ANNOTATE_FUNCTION(x)=__attribute__((annotate(#x)))","-IE:\\QT\\Tools\\QtCreator\\share\\qtcreator\\cplusplus\\wrappedMingwHeaders","-IE:\\QT\\Tools\\QtCreator\\share\\qtcreator\\cplusplus\\wrappedQtHeaders","-IE:\\QT\\Tools\\QtCreator\\share\\qtcreator\\cplusplus\\wrappedQtHeaders\\QtCore","-ID:\\SkullKing_Game\\SkullKing","-IE:\\QT\\6.7.2\\mingw_64\\include","-IE:\\QT\\6.7.2\\mingw_64\\include\\QtWidgets","-IE:\\QT\\6.7.2\\mingw_64\\include\\QtGui","-IE:\\QT\\6.7.2\\mingw_64\\include\\QtNetwork","-IE:\\QT\\6.7.2\\mingw_64\\include\\QtCore","-ID:\\SkullKing_Game\\SkullKing\\build\\Desktop_Qt_6_7_2_MinGW_64_bit-Release\\release","-ID:\\SkullKing_Game\\SkullKing\\build\\Desktop_Qt_6_7_2_MinGW_64_bit-Release","-IE:\\QT\\6.7.2\\mingw_64\\mkspecs\\win32-g++","-isystem","E:\\QT\\Tools\\mingw1120_64\\lib\\gcc\\x86_64-w64-mingw32\\11.2.0\\include\\c++","-isystem","E:\\QT\\Tools\\mingw1120_64\\lib\\gcc\\x86_64-w64-mingw32\\11.2.0\\include\\c++\\x86_64-w64-mingw32","-isystem","E:\\QT\\Tools\\mingw1120_64\\lib\\gcc\\x86_64-w64-mingw32\\11.2.0\\include\\c++\\backward","-isystem","E:\\QT\\Tools\\QtCreator\\bin\\clang\\lib\\clang\\17\\include","-isystem","E:\\QT\\Tools\\mingw1120_64\\x86_64-w64-mingw32\\include","-fmessage-length=0","-fdiagnostics-show-note-include-stack","-fretain-comments-from-system-headers","-fmacro-backtrace-limit=0","-ferror-limit=1000","-x","c++","D:\\SkullKing_Game\\SkullKing\\forgetpassword.cpp"],"directory":"D:/SkullKing_Game/SkullKing/build/Desktop_Qt_6_7_2_MinGW_64_bit-Release/.qtc_clangd","file":"D:/SkullKing_Game/SkullKing/forgetpassword.cpp"},{"arguments":["clang","-Wno-documentation-unknown-command","-Wno-unknown-warning-option","-Wno-unknown-pragmas","-nostdinc","-nostdinc++","-std=gnu++1z","-Wall","-Wextra","-Wextra","-fexceptions","-mthreads","-fsyntax-only","-m64","--target=x86_64-w64-mingw32","-DUNICODE","-D_UNICODE","-DWIN32","-DMINGW_HAS_SECURE_API","-DQT_NO_DEBUG","-DQT_WIDGETS_LIB","-DQT_GUI_LIB","-DQT_NETWORK_LIB","-DQT_CORE_LIB","-DQT_NEEDS_QMAIN","-DQ_CREATOR_RUN","-DQT_ANNOTATE_FUNCTION(x)=__attribute__((annotate(#x)))","-IE:\\QT\\Tools\\QtCreator\\share\\qtcreator\\cplusplus\\wrappedMingwHeaders","-IE:\\QT\\Tools\\QtCreator\\share\\qtcreator\\cplusplus\\wrappedQtHeaders","-IE:\\QT\\Tools\\QtCreator\\share\\qtcreator\\cplusplus\\wrappedQtHeaders\\QtCore","-ID:\\SkullKing_Game\\SkullKing","-IE:\\QT\\6.7.2\\mingw_64\\include","-IE:\\QT\\6.7.2\\mingw_64\\include\\QtWidgets","-IE:\\QT\\6.7.2\\mingw_64\\include\\QtGui","-IE:\\QT\\6.7.2\\mingw_64\\include\\QtNetwork","-IE:\\QT\\6.7.2\\mingw_64\\include\\QtCore","-ID:\\SkullKing_Game\\SkullKing\\build\\Desktop_Qt_6_7_2_MinGW_64_bit-Release\\release","-ID:\\SkullKing_Game\\SkullKing\\build\\Desktop_Qt_6_7_2_MinGW_64_bit-Release","-IE:\\QT\\6.7.2\\mingw_64\\mkspecs\\win32-g++","-isystem","E:\\QT\\Tools\\mingw1120_64\\lib\\gcc\\x86_64-w64-mingw32\\11.2.0\\include\\c++","-isystem","E:\\QT\\Tools\\mingw1120_64\\lib\\gcc\\x86_64-w64-mingw32\\11.2.0\\include\\c++\\x86_64-w64-mingw32","-isystem","E:\\QT\\Tools\\mingw1120_64\\lib\\gcc\\x86_64-w64-mingw32\\11.2.0\\include\\c++\\backward","-isystem","E:\\QT\\Tools\\QtCreator\\bin\\clang\\lib\\clang\\17\\include","-isystem","E:\\QT\\Tools\\mingw1120_64\\x86_64-w64-mingw32\\include","-fmessage-length=0","-fdiagnostics-show-note-include-stack","-fretain-comments-from-system-headers","-fmacro-backtrace-limit=0","-ferror-limit=1000","-x","c++","D:\\SkullKing_Game\\SkullKing\\history.cpp"],"directory":"D:/SkullKing_Game/SkullKing/build/Desktop_Qt_6_7_2_MinGW_64_bit-Release/.qtc_clangd","file":"D:/SkullKing_Game/SkullKing/history.cpp"},{"arguments":["clang","-Wno-documentation-unknown-command","-Wno-unknown-warning-option","-Wno-unknown-pragmas","-nostdinc","-nostdinc++","-std=gnu++1z","-Wall","-Wextra","-Wextra","-fexceptions","-mthreads","-fsyntax-only","-m64","--target=x86_64-w64-mingw32","-DUNICODE","-D_UNICODE","-DWIN32","-DMINGW_HAS_SECURE_API","-DQT_NO_DEBUG","-DQT_WIDGETS_LIB","-DQT_GUI_LIB","-DQT_NETWORK_LIB","-DQT_CORE_LIB","-DQT_NEEDS_QMAIN","-DQ_CREATOR_RUN","-DQT_ANNOTATE_FUNCTION(x)=__attribute__((annotate(#x)))","-IE:\\QT\\Tools\\QtCreator\\share\\qtcreator\\cplusplus\\wrappedMingwHeaders","-IE:\\QT\\Tools\\QtCreator\\share\\qtcreator\\cplusplus\\wrappedQtHeaders","-IE:\\QT\\Tools\\QtCreator\\share\\qtcreator\\cplusplus\\wrappedQtHeaders\\QtCore","-ID:\\SkullKing_Game\\SkullKing","-IE:\\QT\\6.7.2\\mingw_64\\include","-IE:\\QT\\6.7.2\\mingw_64\\include\\QtWidgets","-IE:\\QT\\6.7.2\\mingw_64\\include\\QtGui","-IE:\\QT\\6.7.2\\mingw_64\\include\\QtNetwork","-IE:\\QT\\6.7.2\\mingw_64\\include\\QtCore","-ID:\\SkullKing_Game\\SkullKing\\build\\Desktop_Qt_6_7_2_MinGW_64_bit-Release\\release","-ID:\\SkullKing_Game\\SkullKing\\build\\Desktop_Qt_6_7_2_MinGW_64_bit-Release","-IE:\\QT\\6.7.2\\mingw_64\\mkspecs\\win32-g++","-isystem","E:\\QT\\Tools\\mingw1120_64\\lib\\gcc\\x86_64-w64-mingw32\\11.2.0\\include\\c++","-isystem","E:\\QT\\Tools\\mingw1120_64\\lib\\gcc\\x86_64-w64-mingw32\\11.2.0\\include\\c++\\x86_64-w64-mingw32","-isystem","E:\\QT\\Tools\\mingw1120_64\\lib\\gcc\\x86_64-w64-mingw32\\11.2.0\\include\\c++\\backward","-isystem","E:\\QT\\Tools\\QtCreator\\bin\\clang\\lib\\clang\\17\\include","-isystem","E:\\QT\\Tools\\mingw1120_64\\x86_64-w64-mingw32\\include","-fmessage-length=0","-fdiagnostics-show-note-include-stack","-fretain-comments-from-system-headers","-fmacro-backtrace-limit=0","-ferror-limit=1000","-x","c++","D:\\SkullKing_Game\\SkullKing\\importantcards.cpp"],"directory":"D:/SkullKing_Game/SkullKing/build/Desktop_Qt_6_7_2_MinGW_64_bit-Release/.qtc_clangd","file":"D:/SkullKing_Game/SkullKing/importantcards.cpp"},{"arguments":["clang","-Wno-documentation-unknown-command","-Wno-unknown-warning-option","-Wno-unknown-pragmas","-nostdinc","-nostdinc++","-std=gnu++1z","-Wall","-Wextra","-Wextra","-fexceptions","-mthreads","-fsyntax-only","-m64","--target=x86_64-w64-mingw32","-DUNICODE","-D_UNICODE","-DWIN32","-DMINGW_HAS_SECURE_API","-DQT_NO_DEBUG","-DQT_WIDGETS_LIB","-DQT_GUI_LIB","-DQT_NETWORK_LIB","-DQT_CORE_LIB","-DQT_NEEDS_QMAIN","-DQ_CREATOR_RUN","-DQT_ANNOTATE_FUNCTION(x)=__attribute__((annotate(#x)))","-IE:\\QT\\Tools\\QtCreator\\share\\qtcreator\\cplusplus\\wrappedMingwHeaders","-IE:\\QT\\Tools\\QtCreator\\share\\qtcreator\\cplusplus\\wrappedQtHeaders","-IE:\\QT\\Tools\\QtCreator\\share\\qtcreator\\cplusplus\\wrappedQtHeaders\\QtCore","-ID:\\SkullKing_Game\\SkullKing","-IE:\\QT\\6.7.2\\mingw_64\\include","-IE:\\QT\\6.7.2\\mingw_64\\include\\QtWidgets","-IE:\\QT\\6.7.2\\mingw_64\\include\\QtGui","-IE:\\QT\\6.7.2\\mingw_64\\include\\QtNetwork","-IE:\\QT\\6.7.2\\mingw_64\\include\\QtCore","-ID:\\SkullKing_Game\\SkullKing\\build\\Desktop_Qt_6_7_2_MinGW_64_bit-Release\\release","-ID:\\SkullKing_Game\\SkullKing\\build\\Desktop_Qt_6_7_2_MinGW_64_bit-Release","-IE:\\QT\\6.7.2\\mingw_64\\mkspecs\\win32-g++","-isystem","E:\\QT\\Tools\\mingw1120_64\\lib\\gcc\\x86_64-w64-mingw32\\11.2.0\\include\\c++","-isystem","E:\\QT\\Tools\\mingw1120_64\\lib\\gcc\\x86_64-w64-mingw32\\11.2.0\\include\\c++\\x86_64-w64-mingw32","-isystem","E:\\QT\\Tools\\mingw1120_64\\lib\\gcc\\x86_64-w64-mingw32\\11.2.0\\include\\c++\\backward","-isystem","E:\\QT\\Tools\\QtCreator\\bin\\clang\\lib\\clang\\17\\include","-isystem","E:\\QT\\Tools\\mingw1120_64\\x86_64-w64-mingw32\\include","-fmessage-length=0","-fdiagnostics-show-note-include-stack","-fretain-comments-from-system-headers","-fmacro-backtrace-limit=0","-ferror-limit=1000","-x","c++","D:\\SkullKing_Game\\SkullKing\\main.cpp"],"directory":"D:/SkullKing_Game/SkullKing/build/Desktop_Qt_6_7_2_MinGW_64_bit-Release/.qtc_clangd","file":"D:/SkullKing_Game/SkullKing/main.cpp"},{"arguments":["clang","-Wno-documentation-unknown-command","-Wno-unknown-warning-option","-Wno-unknown-pragmas","-nostdinc","-nostdinc++","-std=gnu++1z","-Wall","-Wextra","-Wextra","-fexceptions","-mthreads","-fsyntax-only","-m64","--target=x86_64-w64-mingw32","-DUNICODE","-D_UNICODE","-DWIN32","-DMINGW_HAS_SECURE_API","-DQT_NO_DEBUG","-DQT_WIDGETS_LIB","-DQT_GUI_LIB","-DQT_NETWORK_LIB","-DQT_CORE_LIB","-DQT_NEEDS_QMAIN","-DQ_CREATOR_RUN","-DQT_ANNOTATE_FUNCTION(x)=__attribute__((annotate(#x)))","-IE:\\QT\\Tools\\QtCreator\\share\\qtcreator\\cplusplus\\wrappedMingwHeaders","-IE:\\QT\\Tools\\QtCreator\\share\\qtcreator\\cplusplus\\wrappedQtHeaders","-IE:\\QT\\Tools\\QtCreator\\share\\qtcreator\\cplusplus\\wrappedQtHeaders\\QtCore","-ID:\\SkullKing_Game\\SkullKing","-IE:\\QT\\6.7.2\\mingw_64\\include","-IE:\\QT\\6.7.2\\mingw_64\\include\\QtWidgets","-IE:\\QT\\6.7.2\\mingw_64\\include\\QtGui","-IE:\\QT\\6.7.2\\mingw_64\\include\\QtNetwork","-IE:\\QT\\6.7.2\\mingw_64\\include\\QtCore","-ID:\\SkullKing_Game\\SkullKing\\build\\Desktop_Qt_6_7_2_MinGW_64_bit-Release\\release","-ID:\\SkullKing_Game\\SkullKing\\build\\Desktop_Qt_6_7_2_MinGW_64_bit-Release","-IE:\\QT\\6.7.2\\mingw_64\\mkspecs\\win32-g++","-isystem","E:\\QT\\Tools\\mingw1120_64\\lib\\gcc\\x86_64-w64-mingw32\\11.2.0\\include\\c++","-isystem","E:\\QT\\Tools\\mingw1120_64\\lib\\gcc\\x86_64-w64-mingw32\\11.2.0\\include\\c++\\x86_64-w64-mingw32","-isystem","E:\\QT\\Tools\\mingw1120_64\\lib\\gcc\\x86_64-w64-mingw32\\11.2.0\\include\\c++\\backward","-isystem","E:\\QT\\Tools\\QtCreator\\bin\\clang\\lib\\clang\\17\\include","-isystem","E:\\QT\\Tools\\mingw1120_64\\x86_64-w64-mingw32\\include","-fmessage-length=0","-fdiagnostics-show-note-include-stack","-fretain-comments-from-system-headers","-fmacro-backtrace-limit=0","-ferror-limit=1000","-x","c++","D:\\SkullKing_Game\\SkullKing\\menu.cpp"],"directory":"D:/SkullKing_Game/SkullKing/build/Desktop_Qt_6_7_2_MinGW_64_bit-Release/.qtc_clangd","file":"D:/SkullKing_Game/SkullKing/menu.cpp"},{"arguments":["clang","-Wno-documentation-unknown-command","-Wno-unknown-warning-option","-Wno-unknown-pragmas","-nostdinc","-nostdinc++","-std=gnu++1z","-Wall","-Wextra","-Wextra","-fexceptions","-mthreads","-fsyntax-only","-m64","--target=x86_64-w64-mingw32","-DUNICODE","-D_UNICODE","-DWIN32","-DMINGW_HAS_SECURE_API","-DQT_NO_DEBUG","-DQT_WIDGETS_LIB","-DQT_GUI_LIB","-DQT_NETWORK_LIB","-DQT_CORE_LIB","-DQT_NEEDS_QMAIN","-DQ_CREATOR_RUN","-DQT_ANNOTATE_FUNCTION(x)=__attribute__((annotate(#x)))","-IE:\\QT\\Tools\\QtCreator\\share\\qtcreator\\cplusplus\\wrappedMingwHeaders","-IE:\\QT\\Tools\\QtCreator\\share\\qtcreator\\cplusplus\\wrappedQtHeaders","-IE:\\QT\\Tools\\QtCreator\\share\\qtcreator\\cplusplus\\wrappedQtHeaders\\QtCore","-ID:\\SkullKing_Game\\SkullKing","-IE:\\QT\\6.7.2\\mingw_64\\include","-IE:\\QT\\6.7.2\\mingw_64\\include\\QtWidgets","-IE:\\QT\\6.7.2\\mingw_64\\include\\QtGui","-IE:\\QT\\6.7.2\\mingw_64\\include\\QtNetwork","-IE:\\QT\\6.7.2\\mingw_64\\include\\QtCore","-ID:\\SkullKing_Game\\SkullKing\\build\\Desktop_Qt_6_7_2_MinGW_64_bit-Release\\release","-ID:\\SkullKing_Game\\SkullKing\\build\\Desktop_Qt_6_7_2_MinGW_64_bit-Release","-IE:\\QT\\6.7.2\\mingw_64\\mkspecs\\win32-g++","-isystem","E:\\QT\\Tools\\mingw1120_64\\lib\\gcc\\x86_64-w64-mingw32\\11.2.0\\include\\c++","-isystem","E:\\QT\\Tools\\mingw1120_64\\lib\\gcc\\x86_64-w64-mingw32\\11.2.0\\include\\c++\\x86_64-w64-mingw32","-isystem","E:\\QT\\Tools\\mingw1120_64\\lib\\gcc\\x86_64-w64-mingw32\\11.2.0\\include\\c++\\backward","-isystem","E:\\QT\\Tools\\QtCreator\\bin\\clang\\lib\\clang\\17\\include","-isystem","E:\\QT\\Tools\\mingw1120_64\\x86_64-w64-mingw32\\include","-fmessage-length=0","-fdiagnostics-show-note-include-stack","-fretain-comments-from-system-headers","-fmacro-backtrace-limit=0","-ferror-limit=1000","-x","c++","D:\\SkullKing_Game\\SkullKing\\player.cpp"],"directory":"D:/SkullKing_Game/SkullKing/build/Desktop_Qt_6_7_2_MinGW_64_bit-Release/.qtc_clangd","file":"D:/SkullKing_Game/SkullKing/player.cpp"},{"arguments":["clang","-Wno-documentation-unknown-command","-Wno-unknown-warning-option","-Wno-unknown-pragmas","-nostdinc","-nostdinc++","-std=gnu++1z","-Wall","-Wextra","-Wextra","-fexceptions","-mthreads","-fsyntax-only","-m64","--target=x86_64-w64-mingw32","-DUNICODE","-D_UNICODE","-DWIN32","-DMINGW_HAS_SECURE_API","-DQT_NO_DEBUG","-DQT_WIDGETS_LIB","-DQT_GUI_LIB","-DQT_NETWORK_LIB","-DQT_CORE_LIB","-DQT_NEEDS_QMAIN","-DQ_CREATOR_RUN","-DQT_ANNOTATE_FUNCTION(x)=__attribute__((annotate(#x)))","-IE:\\QT\\Tools\\QtCreator\\share\\qtcreator\\cplusplus\\wrappedMingwHeaders","-IE:\\QT\\Tools\\QtCreator\\share\\qtcreator\\cplusplus\\wrappedQtHeaders","-IE:\\QT\\Tools\\QtCreator\\share\\qtcreator\\cplusplus\\wrappedQtHeaders\\QtCore","-ID:\\SkullKing_Game\\SkullKing","-IE:\\QT\\6.7.2\\mingw_64\\include","-IE:\\QT\\6.7.2\\mingw_64\\include\\QtWidgets","-IE:\\QT\\6.7.2\\mingw_64\\include\\QtGui","-IE:\\QT\\6.7.2\\mingw_64\\include\\QtNetwork","-IE:\\QT\\6.7.2\\mingw_64\\include\\QtCore","-ID:\\SkullKing_Game\\SkullKing\\build\\Desktop_Qt_6_7_2_MinGW_64_bit-Release\\release","-ID:\\SkullKing_Game\\SkullKing\\build\\Desktop_Qt_6_7_2_MinGW_64_bit-Release","-IE:\\QT\\6.7.2\\mingw_64\\mkspecs\\win32-g++","-isystem","E:\\QT\\Tools\\mingw1120_64\\lib\\gcc\\x86_64-w64-mingw32\\11.2.0\\include\\c++","-isystem","E:\\QT\\Tools\\mingw1120_64\\lib\\gcc\\x86_64-w64-mingw32\\11.2.0\\include\\c++\\x86_64-w64-mingw32","-isystem","E:\\QT\\Tools\\mingw1120_64\\lib\\gcc\\x86_64-w64-mingw32\\11.2.0\\include\\c++\\backward","-isystem","E:\\QT\\Tools\\QtCreator\\bin\\clang\\lib\\clang\\17\\include","-isystem","E:\\QT\\Tools\\mingw1120_64\\x86_64-w64-mingw32\\include","-fmessage-length=0","-fdiagnostics-show-note-include-stack","-fretain-comments-from-system-headers","-fmacro-backtrace-limit=0","-ferror-limit=1000","-x","c++","D:\\SkullKing_Game\\SkullKing\\server.cpp"],"directory":"D:/SkullKing_Game/SkullKing/build/Desktop_Qt_6_7_2_MinGW_64_bit-Release/.qtc_clangd","file":"D:/SkullKing_Game/SkullKing/server.cpp"},{"arguments":["clang","-Wno-documentation-unknown-command","-Wno-unknown-warning-option","-Wno-unknown-pragmas","-nostdinc","-nostdinc++","-std=gnu++1z","-Wall","-Wextra","-Wextra","-fexceptions","-mthreads","-fsyntax-only","-m64","--target=x86_64-w64-mingw32","-DUNICODE","-D_UNICODE","-DWIN32","-DMINGW_HAS_SECURE_API","-DQT_NO_DEBUG","-DQT_WIDGETS_LIB","-DQT_GUI_LIB","-DQT_NETWORK_LIB","-DQT_CORE_LIB","-DQT_NEEDS_QMAIN","-DQ_CREATOR_RUN","-DQT_ANNOTATE_FUNCTION(x)=__attribute__((annotate(#x)))","-IE:\\QT\\Tools\\QtCreator\\share\\qtcreator\\cplusplus\\wrappedMingwHeaders","-IE:\\QT\\Tools\\QtCreator\\share\\qtcreator\\cplusplus\\wrappedQtHeaders","-IE:\\QT\\Tools\\QtCreator\\share\\qtcreator\\cplusplus\\wrappedQtHeaders\\QtCore","-ID:\\SkullKing_Game\\SkullKing","-IE:\\QT\\6.7.2\\mingw_64\\include","-IE:\\QT\\6.7.2\\mingw_64\\include\\QtWidgets","-IE:\\QT\\6.7.2\\mingw_64\\include\\QtGui","-IE:\\QT\\6.7.2\\mingw_64\\include\\QtNetwork","-IE:\\QT\\6.7.2\\mingw_64\\include\\QtCore","-ID:\\SkullKing_Game\\SkullKing\\build\\Desktop_Qt_6_7_2_MinGW_64_bit-Release\\release","-ID:\\SkullKing_Game\\SkullKing\\build\\Desktop_Qt_6_7_2_MinGW_64_bit-Release","-IE:\\QT\\6.7.2\\mingw_64\\mkspecs\\win32-g++","-isystem","E:\\QT\\Tools\\mingw1120_64\\lib\\gcc\\x86_64-w64-mingw32\\11.2.0\\include\\c++","-isystem","E:\\QT\\Tools\\mingw1120_64\\lib\\gcc\\x86_64-w64-mingw32\\11.2.0\\include\\c++\\x86_64-w64-mingw32","-isystem","E:\\QT\\Tools\\mingw1120_64\\lib\\gcc\\x86_64-w64-mingw32\\11.2.0\\include\\c++\\backward","-isystem","E:\\QT\\Tools\\QtCreator\\bin\\clang\\lib\\clang\\17\\include","-isystem","E:\\QT\\Tools\\mingw1120_64\\x86_64-w64-mingw32\\include","-fmessage-length=0","-fdiagnostics-show-note-include-stack","-fretain-comments-from-system-headers","-fmacro-backtrace-limit=0","-ferror-limit=1000","-x","c++","D:\\SkullKing_Game\\SkullKing\\signin.cpp"],"directory":"D:/SkullKing_Game/SkullKing/build/Desktop_Qt_6_7_2_MinGW_64_bit-Release/.qtc_clangd","file":"D:/SkullKing_Game/SkullKing/signin.cpp"},{"arguments":["clang","-Wno-documentation-unknown-command","-Wno-unknown-warning-option","-Wno-unknown-pragmas","-nostdinc","-nostdinc++","-std=gnu++1z","-Wall","-Wextra","-Wextra","-fexceptions","-mthreads","-fsyntax-only","-m64","--target=x86_64-w64-mingw32","-DUNICODE","-D_UNICODE","-DWIN32","-DMINGW_HAS_SECURE_API","-DQT_NO_DEBUG","-DQT_WIDGETS_LIB","-DQT_GUI_LIB","-DQT_NETWORK_LIB","-DQT_CORE_LIB","-DQT_NEEDS_QMAIN","-DQ_CREATOR_RUN","-DQT_ANNOTATE_FUNCTION(x)=__attribute__((annotate(#x)))","-IE:\\QT\\Tools\\QtCreator\\share\\qtcreator\\cplusplus\\wrappedMingwHeaders","-IE:\\QT\\Tools\\QtCreator\\share\\qtcreator\\cplusplus\\wrappedQtHeaders","-IE:\\QT\\Tools\\QtCreator\\share\\qtcreator\\cplusplus\\wrappedQtHeaders\\QtCore","-ID:\\SkullKing_Game\\SkullKing","-IE:\\QT\\6.7.2\\mingw_64\\include","-IE:\\QT\\6.7.2\\mingw_64\\include\\QtWidgets","-IE:\\QT\\6.7.2\\mingw_64\\include\\QtGui","-IE:\\QT\\6.7.2\\mingw_64\\include\\QtNetwork","-IE:\\QT\\6.7.2\\mingw_64\\include\\QtCore","-ID:\\SkullKing_Game\\SkullKing\\build\\Desktop_Qt_6_7_2_MinGW_64_bit-Release\\release","-ID:\\SkullKing_Game\\SkullKing\\build\\Desktop_Qt_6_7_2_MinGW_64_bit-Release","-IE:\\QT\\6.7.2\\mingw_64\\mkspecs\\win32-g++","-isystem","E:\\QT\\Tools\\mingw1120_64\\lib\\gcc\\x86_64-w64-mingw32\\11.2.0\\include\\c++","-isystem","E:\\QT\\Tools\\mingw1120_64\\lib\\gcc\\x86_64-w64-mingw32\\11.2.0\\include\\c++\\x86_64-w64-mingw32","-isystem","E:\\QT\\Tools\\mingw1120_64\\lib\\gcc\\x86_64-w64-mingw32\\11.2.0\\include\\c++\\backward","-isystem","E:\\QT\\Tools\\QtCreator\\bin\\clang\\lib\\clang\\17\\include","-isystem","E:\\QT\\Tools\\mingw1120_64\\x86_64-w64-mingw32\\include","-fmessage-length=0","-fdiagnostics-show-note-include-stack","-fretain-comments-from-system-headers","-fmacro-backtrace-limit=0","-ferror-limit=1000","-x","c++","D:\\SkullKing_Game\\SkullKing\\signup.cpp"],"directory":"D:/SkullKing_Game/SkullKing/build/Desktop_Qt_6_7_2_MinGW_64_bit-Release/.qtc_clangd","file":"D:/SkullKing_Game/SkullKing/signup.cpp"},{"arguments":["clang","-Wno-documentation-unknown-command","-Wno-unknown-warning-option","-Wno-unknown-pragmas","-nostdinc","-nostdinc++","-std=gnu++1z","-Wall","-Wextra","-Wextra","-fexceptions","-mthreads","-fsyntax-only","-m64","--target=x86_64-w64-mingw32","-DUNICODE","-D_UNICODE","-DWIN32","-DMINGW_HAS_SECURE_API","-DQT_NO_DEBUG","-DQT_WIDGETS_LIB","-DQT_GUI_LIB","-DQT_NETWORK_LIB","-DQT_CORE_LIB","-DQT_NEEDS_QMAIN","-DQ_CREATOR_RUN","-DQT_ANNOTATE_FUNCTION(x)=__attribute__((annotate(#x)))","-IE:\\QT\\Tools\\QtCreator\\share\\qtcreator\\cplusplus\\wrappedMingwHeaders","-IE:\\QT\\Tools\\QtCreator\\share\\qtcreator\\cplusplus\\wrappedQtHeaders","-IE:\\QT\\Tools\\QtCreator\\share\\qtcreator\\cplusplus\\wrappedQtHeaders\\QtCore","-ID:\\SkullKing_Game\\SkullKing","-IE:\\QT\\6.7.2\\mingw_64\\include","-IE:\\QT\\6.7.2\\mingw_64\\include\\QtWidgets","-IE:\\QT\\6.7.2\\mingw_64\\include\\QtGui","-IE:\\QT\\6.7.2\\mingw_64\\include\\QtNetwork","-IE:\\QT\\6.7.2\\mingw_64\\include\\QtCore","-ID:\\SkullKing_Game\\SkullKing\\build\\Desktop_Qt_6_7_2_MinGW_64_bit-Release\\release","-ID:\\SkullKing_Game\\SkullKing\\build\\Desktop_Qt_6_7_2_MinGW_64_bit-Release","-IE:\\QT\\6.7.2\\mingw_64\\mkspecs\\win32-g++","-isystem","E:\\QT\\Tools\\mingw1120_64\\lib\\gcc\\x86_64-w64-mingw32\\11.2.0\\include\\c++","-isystem","E:\\QT\\Tools\\mingw1120_64\\lib\\gcc\\x86_64-w64-mingw32\\11.2.0\\include\\c++\\x86_64-w64-mingw32","-isystem","E:\\QT\\Tools\\mingw1120_64\\lib\\gcc\\x86_64-w64-mingw32\\11.2.0\\include\\c++\\backward","-isystem","E:\\QT\\Tools\\QtCreator\\bin\\clang\\lib\\clang\\17\\include","-isystem","E:\\QT\\Tools\\mingw1120_64\\x86_64-w64-mingw32\\include","-fmessage-length=0","-fdiagnostics-show-note-include-stack","-fretain-comments-from-system-headers","-fmacro-backtrace-limit=0","-ferror-limit=1000","-x","c++","D:\\SkullKing_Game\\SkullKing\\skullking.cpp"],"directory":"D:/SkullKing_Game/SkullKing/build/Desktop_Qt_6_7_2_MinGW_64_bit-Release/.qtc_clangd","file":"D:/SkullKing_Game/SkullKing/skullking.cpp"},{"arguments":["clang","-Wno-documentation-unknown-command","-Wno-unknown-warning-option","-Wno-unknown-pragmas","-nostdinc","-nostdinc++","-std=gnu++1z","-Wall","-Wextra","-Wextra","-fexceptions","-mthreads","-fsyntax-only","-m64","--target=x86_64-w64-mingw32","-DUNICODE","-D_UNICODE","-DWIN32","-DMINGW_HAS_SECURE_API","-DQT_NO_DEBUG","-DQT_WIDGETS_LIB","-DQT_GUI_LIB","-DQT_NETWORK_LIB","-DQT_CORE_LIB","-DQT_NEEDS_QMAIN","-DQ_CREATOR_RUN","-DQT_ANNOTATE_FUNCTION(x)=__attribute__((annotate(#x)))","-IE:\\QT\\Tools\\QtCreator\\share\\qtcreator\\cplusplus\\wrappedMingwHeaders","-IE:\\QT\\Tools\\QtCreator\\share\\qtcreator\\cplusplus\\wrappedQtHeaders","-IE:\\QT\\Tools\\QtCreator\\share\\qtcreator\\cplusplus\\wrappedQtHeaders\\QtCore","-ID:\\SkullKing_Game\\SkullKing","-IE:\\QT\\6.7.2\\mingw_64\\include","-IE:\\QT\\6.7.2\\mingw_64\\include\\QtWidgets","-IE:\\QT\\6.7.2\\mingw_64\\include\\QtGui","-IE:\\QT\\6.7.2\\mingw_64\\include\\QtNetwork","-IE:\\QT\\6.7.2\\mingw_64\\include\\QtCore","-ID:\\SkullKing_Game\\SkullKing\\build\\Desktop_Qt_6_7_2_MinGW_64_bit-Release\\release","-ID:\\SkullKing_Game\\SkullKing\\build\\Desktop_Qt_6_7_2_MinGW_64_bit-Release","-IE:\\QT\\6.7.2\\mingw_64\\mkspecs\\win32-g++","-isystem","E:\\QT\\Tools\\mingw1120_64\\lib\\gcc\\x86_64-w64-mingw32\\11.2.0\\include\\c++","-isystem","E:\\QT\\Tools\\mingw1120_64\\lib\\gcc\\x86_64-w64-mingw32\\11.2.0\\include\\c++\\x86_64-w64-mingw32","-isystem","E:\\QT\\Tools\\mingw1120_64\\lib\\gcc\\x86_64-w64-mingw32\\11.2.0\\include\\c++\\backward","-isystem","E:\\QT\\Tools\\QtCreator\\bin\\clang\\lib\\clang\\17\\include","-isystem","E:\\QT\\Tools\\mingw1120_64\\x86_64-w64-mingw32\\include","-fmessage-length=0","-fdiagnostics-show-note-include-stack","-fretain-comments-from-system-headers","-fmacro-backtrace-limit=0","-ferror-limit=1000","-x","c++-header","D:\\SkullKing_Game\\SkullKing\\SlowTyper.h"],"directory":"D:/SkullKing_Game/SkullKing/build/Desktop_Qt_6_7_2_MinGW_64_bit-Release/.qtc_clangd","file":"D:/SkullKing_Game/SkullKing/SlowTyper.h"},{"arguments":["clang","-Wno-documentation-unknown-command","-Wno-unknown-warning-option","-Wno-unknown-pragmas","-nostdinc","-nostdinc++","-std=gnu++1z","-Wall","-Wextra","-Wextra","-fexceptions","-mthreads","-fsyntax-only","-m64","--target=x86_64-w64-mingw32","-DUNICODE","-D_UNICODE","-DWIN32","-DMINGW_HAS_SECURE_API","-DQT_NO_DEBUG","-DQT_WIDGETS_LIB","-DQT_GUI_LIB","-DQT_NETWORK_LIB","-DQT_CORE_LIB","-DQT_NEEDS_QMAIN","-DQ_CREATOR_RUN","-DQT_ANNOTATE_FUNCTION(x)=__attribute__((annotate(#x)))","-IE:\\QT\\Tools\\QtCreator\\share\\qtcreator\\cplusplus\\wrappedMingwHeaders","-IE:\\QT\\Tools\\QtCreator\\share\\qtcreator\\cplusplus\\wrappedQtHeaders","-IE:\\QT\\Tools\\QtCreator\\share\\qtcreator\\cplusplus\\wrappedQtHeaders\\QtCore","-ID:\\SkullKing_Game\\SkullKing","-IE:\\QT\\6.7.2\\mingw_64\\include","-IE:\\QT\\6.7.2\\mingw_64\\include\\QtWidgets","-IE:\\QT\\6.7.2\\mingw_64\\include\\QtGui","-IE:\\QT\\6.7.2\\mingw_64\\include\\QtNetwork","-IE:\\QT\\6.7.2\\mingw_64\\include\\QtCore","-ID:\\SkullKing_Game\\SkullKing\\build\\Desktop_Qt_6_7_2_MinGW_64_bit-Release\\release","-ID:\\SkullKing_Game\\SkullKing\\build\\Desktop_Qt_6_7_2_MinGW_64_bit-Release","-IE:\\QT\\6.7.2\\mingw_64\\mkspecs\\win32-g++","-isystem","E:\\QT\\Tools\\mingw1120_64\\lib\\gcc\\x86_64-w64-mingw32\\11.2.0\\include\\c++","-isystem","E:\\QT\\Tools\\mingw1120_64\\lib\\gcc\\x86_64-w64-mingw32\\11.2.0\\include\\c++\\x86_64-w64-mingw32","-isystem","E:\\QT\\Tools\\mingw1120_64\\lib\\gcc\\x86_64-w64-mingw32\\11.2.0\\include\\c++\\backward","-isystem","E:\\QT\\Tools\\QtCreator\\bin\\clang\\lib\\clang\\17\\include","-isystem","E:\\QT\\Tools\\mingw1120_64\\x86_64-w64-mingw32\\include","-fmessage-length=0","-fdiagnostics-show-note-include-stack","-fretain-comments-from-system-headers","-fmacro-backtrace-limit=0","-ferror-limit=1000","-x","c++-header","D:\\SkullKing_Game\\SkullKing\\cards.h"],"directory":"D:/SkullKing_Game/SkullKing/build/Desktop_Qt_6_7_2_MinGW_64_bit-Release/.qtc_clangd","file":"D:/SkullKing_Game/SkullKing/cards.h"},{"arguments":["clang","-Wno-documentation-unknown-command","-Wno-unknown-warning-option","-Wno-unknown-pragmas","-nostdinc","-nostdinc++","-std=gnu++1z","-Wall","-Wextra","-Wextra","-fexceptions","-mthreads","-fsyntax-only","-m64","--target=x86_64-w64-mingw32","-DUNICODE","-D_UNICODE","-DWIN32","-DMINGW_HAS_SECURE_API","-DQT_NO_DEBUG","-DQT_WIDGETS_LIB","-DQT_GUI_LIB","-DQT_NETWORK_LIB","-DQT_CORE_LIB","-DQT_NEEDS_QMAIN","-DQ_CREATOR_RUN","-DQT_ANNOTATE_FUNCTION(x)=__attribute__((annotate(#x)))","-IE:\\QT\\Tools\\QtCreator\\share\\qtcreator\\cplusplus\\wrappedMingwHeaders","-IE:\\QT\\Tools\\QtCreator\\share\\qtcreator\\cplusplus\\wrappedQtHeaders","-IE:\\QT\\Tools\\QtCreator\\share\\qtcreator\\cplusplus\\wrappedQtHeaders\\QtCore","-ID:\\SkullKing_Game\\SkullKing","-IE:\\QT\\6.7.2\\mingw_64\\include","-IE:\\QT\\6.7.2\\mingw_64\\include\\QtWidgets","-IE:\\QT\\6.7.2\\mingw_64\\include\\QtGui","-IE:\\QT\\6.7.2\\mingw_64\\include\\QtNetwork","-IE:\\QT\\6.7.2\\mingw_64\\include\\QtCore","-ID:\\SkullKing_Game\\SkullKing\\build\\Desktop_Qt_6_7_2_MinGW_64_bit-Release\\release","-ID:\\SkullKing_Game\\SkullKing\\build\\Desktop_Qt_6_7_2_MinGW_64_bit-Release","-IE:\\QT\\6.7.2\\mingw_64\\mkspecs\\win32-g++","-isystem","E:\\QT\\Tools\\mingw1120_64\\lib\\gcc\\x86_64-w64-mingw32\\11.2.0\\include\\c++","-isystem","E:\\QT\\Tools\\mingw1120_64\\lib\\gcc\\x86_64-w64-mingw32\\11.2.0\\include\\c++\\x86_64-w64-mingw32","-isystem","E:\\QT\\Tools\\mingw1120_64\\lib\\gcc\\x86_64-w64-mingw32\\11.2.0\\include\\c++\\backward","-isystem","E:\\QT\\Tools\\QtCreator\\bin\\clang\\lib\\clang\\17\\include","-isystem","E:\\QT\\Tools\\mingw1120_64\\x86_64-w64-mingw32\\include","-fmessage-length=0","-fdiagnostics-show-note-include-stack","-fretain-comments-from-system-headers","-fmacro-backtrace-limit=0","-ferror-limit=1000","-x","c++-header","D:\\SkullKing_Game\\SkullKing\\changeinformation.h"],"directory":"D:/SkullKing_Game/SkullKing/build/Desktop_Qt_6_7_2_MinGW_64_bit-Release/.qtc_clangd","file":"D:/SkullKing_Game/SkullKing/changeinformation.h"},{"arguments":["clang","-Wno-documentation-unknown-command","-Wno-unknown-warning-option","-Wno-unknown-pragmas","-nostdinc","-nostdinc++","-std=gnu++1z","-Wall","-Wextra","-Wextra","-fexceptions","-mthreads","-fsyntax-only","-m64","--target=x86_64-w64-mingw32","-DUNICODE","-D_UNICODE","-DWIN32","-DMINGW_HAS_SECURE_API","-DQT_NO_DEBUG","-DQT_WIDGETS_LIB","-DQT_GUI_LIB","-DQT_NETWORK_LIB","-DQT_CORE_LIB","-DQT_NEEDS_QMAIN","-DQ_CREATOR_RUN","-DQT_ANNOTATE_FUNCTION(x)=__attribute__((annotate(#x)))","-IE:\\QT\\Tools\\QtCreator\\share\\qtcreator\\cplusplus\\wrappedMingwHeaders","-IE:\\QT\\Tools\\QtCreator\\share\\qtcreator\\cplusplus\\wrappedQtHeaders","-IE:\\QT\\Tools\\QtCreator\\share\\qtcreator\\cplusplus\\wrappedQtHeaders\\QtCore","-ID:\\SkullKing_Game\\SkullKing","-IE:\\QT\\6.7.2\\mingw_64\\include","-IE:\\QT\\6.7.2\\mingw_64\\include\\QtWidgets","-IE:\\QT\\6.7.2\\mingw_64\\include\\QtGui","-IE:\\QT\\6.7.2\\mingw_64\\include\\QtNetwork","-IE:\\QT\\6.7.2\\mingw_64\\include\\QtCore","-ID:\\SkullKing_Game\\SkullKing\\build\\Desktop_Qt_6_7_2_MinGW_64_bit-Release\\release","-ID:\\SkullKing_Game\\SkullKing\\build\\Desktop_Qt_6_7_2_MinGW_64_bit-Release","-IE:\\QT\\6.7.2\\mingw_64\\mkspecs\\win32-g++","-isystem","E:\\QT\\Tools\\mingw1120_64\\lib\\gcc\\x86_64-w64-mingw32\\11.2.0\\include\\c++","-isystem","E:\\QT\\Tools\\mingw1120_64\\lib\\gcc\\x86_64-w64-mingw32\\11.2.0\\include\\c++\\x86_64-w64-mingw32","-isystem","E:\\QT\\Tools\\mingw1120_64\\lib\\gcc\\x86_64-w64-mingw32\\11.2.0\\include\\c++\\backward","-isystem","E:\\QT\\Tools\\QtCreator\\bin\\clang\\lib\\clang\\17\\include","-isystem","E:\\QT\\Tools\\mingw1120_64\\x86_64-w64-mingw32\\include","-fmessage-length=0","-fdiagnostics-show-note-include-stack","-fretain-comments-from-system-headers","-fmacro-backtrace-limit=0","-ferror-limit=1000","-x","c++-header","D:\\SkullKing_Game\\SkullKing\\client.h"],"directory":"D:/SkullKing_Game/SkullKing/build/Desktop_Qt_6_7_2_MinGW_64_bit-Release/.qtc_clangd","file":"D:/SkullKing_Game/SkullKing/client.h"},{"arguments":["clang","-Wno-documentation-unknown-command","-Wno-unknown-warning-option","-Wno-unknown-pragmas","-nostdinc","-nostdinc++","-std=gnu++1z","-Wall","-Wextra","-Wextra","-fexceptions","-mthreads","-fsyntax-only","-m64","--target=x86_64-w64-mingw32","-DUNICODE","-D_UNICODE","-DWIN32","-DMINGW_HAS_SECURE_API","-DQT_NO_DEBUG","-DQT_WIDGETS_LIB","-DQT_GUI_LIB","-DQT_NETWORK_LIB","-DQT_CORE_LIB","-DQT_NEEDS_QMAIN","-DQ_CREATOR_RUN","-DQT_ANNOTATE_FUNCTION(x)=__attribute__((annotate(#x)))","-IE:\\QT\\Tools\\QtCreator\\share\\qtcreator\\cplusplus\\wrappedMingwHeaders","-IE:\\QT\\Tools\\QtCreator\\share\\qtcreator\\cplusplus\\wrappedQtHeaders","-IE:\\QT\\Tools\\QtCreator\\share\\qtcreator\\cplusplus\\wrappedQtHeaders\\QtCore","-ID:\\SkullKing_Game\\SkullKing","-IE:\\QT\\6.7.2\\mingw_64\\include","-IE:\\QT\\6.7.2\\mingw_64\\include\\QtWidgets","-IE:\\QT\\6.7.2\\mingw_64\\include\\QtGui","-IE:\\QT\\6.7.2\\mingw_64\\include\\QtNetwork","-IE:\\QT\\6.7.2\\mingw_64\\include\\QtCore","-ID:\\SkullKing_Game\\SkullKing\\build\\Desktop_Qt_6_7_2_MinGW_64_bit-Release\\release","-ID:\\SkullKing_Game\\SkullKing\\build\\Desktop_Qt_6_7_2_MinGW_64_bit-Release","-IE:\\QT\\6.7.2\\mingw_64\\mkspecs\\win32-g++","-isystem","E:\\QT\\Tools\\mingw1120_64\\lib\\gcc\\x86_64-w64-mingw32\\11.2.0\\include\\c++","-isystem","E:\\QT\\Tools\\mingw1120_64\\lib\\gcc\\x86_64-w64-mingw32\\11.2.0\\include\\c++\\x86_64-w64-mingw32","-isystem","E:\\QT\\Tools\\mingw1120_64\\lib\\gcc\\x86_64-w64-mingw32\\11.2.0\\include\\c++\\backward","-isystem","E:\\QT\\Tools\\QtCreator\\bin\\clang\\lib\\clang\\17\\include","-isystem","E:\\QT\\Tools\\mingw1120_64\\x86_64-w64-mingw32\\include","-fmessage-length=0","-fdiagnostics-show-note-include-stack","-fretain-comments-from-system-headers","-fmacro-backtrace-limit=0","-ferror-limit=1000","-x","c++-header","D:\\SkullKing_Game\\SkullKing\\clientorserver.h"],"directory":"D:/SkullKing_Game/SkullKing/build/Desktop_Qt_6_7_2_MinGW_64_bit-Release/.qtc_clangd","file":"D:/SkullKing_Game/SkullKing/clientorserver.h"},{"arguments":["clang","-Wno-documentation-unknown-command","-Wno-unknown-warning-option","-Wno-unknown-pragmas","-nostdinc","-nostdinc++","-std=gnu++1z","-Wall","-Wextra","-Wextra","-fexceptions","-mthreads","-fsyntax-only","-m64","--target=x86_64-w64-mingw32","-DUNICODE","-D_UNICODE","-DWIN32","-DMINGW_HAS_SECURE_API","-DQT_NO_DEBUG","-DQT_WIDGETS_LIB","-DQT_GUI_LIB","-DQT_NETWORK_LIB","-DQT_CORE_LIB","-DQT_NEEDS_QMAIN","-DQ_CREATOR_RUN","-DQT_ANNOTATE_FUNCTION(x)=__attribute__((annotate(#x)))","-IE:\\QT\\Tools\\QtCreator\\share\\qtcreator\\cplusplus\\wrappedMingwHeaders","-IE:\\QT\\Tools\\QtCreator\\share\\qtcreator\\cplusplus\\wrappedQtHeaders","-IE:\\QT\\Tools\\QtCreator\\share\\qtcreator\\cplusplus\\wrappedQtHeaders\\QtCore","-ID:\\SkullKing_Game\\SkullKing","-IE:\\QT\\6.7.2\\mingw_64\\include","-IE:\\QT\\6.7.2\\mingw_64\\include\\QtWidgets","-IE:\\QT\\6.7.2\\mingw_64\\include\\QtGui","-IE:\\QT\\6.7.2\\mingw_64\\include\\QtNetwork","-IE:\\QT\\6.7.2\\mingw_64\\include\\QtCore","-ID:\\SkullKing_Game\\SkullKing\\build\\Desktop_Qt_6_7_2_MinGW_64_bit-Release\\release","-ID:\\SkullKing_Game\\SkullKing\\build\\Desktop_Qt_6_7_2_MinGW_64_bit-Release","-IE:\\QT\\6.7.2\\mingw_64\\mkspecs\\win32-g++","-isystem","E:\\QT\\Tools\\mingw1120_64\\lib\\gcc\\x86_64-w64-mingw32\\11.2.0\\include\\c++","-isystem","E:\\QT\\Tools\\mingw1120_64\\lib\\gcc\\x86_64-w64-mingw32\\11.2.0\\include\\c++\\x86_64-w64-mingw32","-isystem","E:\\QT\\Tools\\mingw1120_64\\lib\\gcc\\x86_64-w64-mingw32\\11.2.0\\include\\c++\\backward","-isystem","E:\\QT\\Tools\\QtCreator\\bin\\clang\\lib\\clang\\17\\include","-isystem","E:\\QT\\Tools\\mingw1120_64\\x86_64-w64-mingw32\\include","-fmessage-length=0","-fdiagnostics-show-note-include-stack","-fretain-comments-from-system-headers","-fmacro-backtrace-limit=0","-ferror-limit=1000","-x","c++-header","D:\\SkullKing_Game\\SkullKing\\common.h"],"directory":"D:/SkullKing_Game/SkullKing/build/Desktop_Qt_6_7_2_MinGW_64_bit-Release/.qtc_clangd","file":"D:/SkullKing_Game/SkullKing/common.h"},{"arguments":["clang","-Wno-documentation-unknown-command","-Wno-unknown-warning-option","-Wno-unknown-pragmas","-nostdinc","-nostdinc++","-std=gnu++1z","-Wall","-Wextra","-Wextra","-fexceptions","-mthreads","-fsyntax-only","-m64","--target=x86_64-w64-mingw32","-DUNICODE","-D_UNICODE","-DWIN32","-DMINGW_HAS_SECURE_API","-DQT_NO_DEBUG","-DQT_WIDGETS_LIB","-DQT_GUI_LIB","-DQT_NETWORK_LIB","-DQT_CORE_LIB","-DQT_NEEDS_QMAIN","-DQ_CREATOR_RUN","-DQT_ANNOTATE_FUNCTION(x)=__attribute__((annotate(#x)))","-IE:\\QT\\Tools\\QtCreator\\share\\qtcreator\\cplusplus\\wrappedMingwHeaders","-IE:\\QT\\Tools\\QtCreator\\share\\qtcreator\\cplusplus\\wrappedQtHeaders","-IE:\\QT\\Tools\\QtCreator\\share\\qtcreator\\cplusplus\\wrappedQtHeaders\\QtCore","-ID:\\SkullKing_Game\\SkullKing","-IE:\\QT\\6.7.2\\mingw_64\\include","-IE:\\QT\\6.7.2\\mingw_64\\include\\QtWidgets","-IE:\\QT\\6.7.2\\mingw_64\\include\\QtGui","-IE:\\QT\\6.7.2\\mingw_64\\include\\QtNetwork","-IE:\\QT\\6.7.2\\mingw_64\\include\\QtCore","-ID:\\SkullKing_Game\\SkullKing\\build\\Desktop_Qt_6_7_2_MinGW_64_bit-Release\\release","-ID:\\SkullKing_Game\\SkullKing\\build\\Desktop_Qt_6_7_2_MinGW_64_bit-Release","-IE:\\QT\\6.7.2\\mingw_64\\mkspecs\\win32-g++","-isystem","E:\\QT\\Tools\\mingw1120_64\\lib\\gcc\\x86_64-w64-mingw32\\11.2.0\\include\\c++","-isystem","E:\\QT\\Tools\\mingw1120_64\\lib\\gcc\\x86_64-w64-mingw32\\11.2.0\\include\\c++\\x86_64-w64-mingw32","-isystem","E:\\QT\\Tools\\mingw1120_64\\lib\\gcc\\x86_64-w64-mingw32\\11.2.0\\include\\c++\\backward","-isystem","E:\\QT\\Tools\\QtCreator\\bin\\clang\\lib\\clang\\17\\include","-isystem","E:\\QT\\Tools\\mingw1120_64\\x86_64-w64-mingw32\\include","-fmessage-length=0","-fdiagnostics-show-note-include-stack","-fretain-comments-from-system-headers","-fmacro-backtrace-limit=0","-ferror-limit=1000","-x","c++-header","D:\\SkullKing_Game\\SkullKing\\forgetpassword.h"],"directory":"D:/SkullKing_Game/SkullKing/build/Desktop_Qt_6_7_2_MinGW_64_bit-Release/.qtc_clangd","file":"D:/SkullKing_Game/SkullKing/forgetpassword.h"},{"arguments":["clang","-Wno-documentation-unknown-command","-Wno-unknown-warning-option","-Wno-unknown-pragmas","-nostdinc","-nostdinc++","-std=gnu++1z","-Wall","-Wextra","-Wextra","-fexceptions","-mthreads","-fsyntax-only","-m64","--target=x86_64-w64-mingw32","-DUNICODE","-D_UNICODE","-DWIN32","-DMINGW_HAS_SECURE_API","-DQT_NO_DEBUG","-DQT_WIDGETS_LIB","-DQT_GUI_LIB","-DQT_NETWORK_LIB","-DQT_CORE_LIB","-DQT_NEEDS_QMAIN","-DQ_CREATOR_RUN","-DQT_ANNOTATE_FUNCTION(x)=__attribute__((annotate(#x)))","-IE:\\QT\\Tools\\QtCreator\\share\\qtcreator\\cplusplus\\wrappedMingwHeaders","-IE:\\QT\\Tools\\QtCreator\\share\\qtcreator\\cplusplus\\wrappedQtHeaders","-IE:\\QT\\Tools\\QtCreator\\share\\qtcreator\\cplusplus\\wrappedQtHeaders\\QtCore","-ID:\\SkullKing_Game\\SkullKing","-IE:\\QT\\6.7.2\\mingw_64\\include","-IE:\\QT\\6.7.2\\mingw_64\\include\\QtWidgets","-IE:\\QT\\6.7.2\\mingw_64\\include\\QtGui","-IE:\\QT\\6.7.2\\mingw_64\\include\\QtNetwork","-IE:\\QT\\6.7.2\\mingw_64\\include\\QtCore","-ID:\\SkullKing_Game\\SkullKing\\build\\Desktop_Qt_6_7_2_MinGW_64_bit-Release\\release","-ID:\\SkullKing_Game\\SkullKing\\build\\Desktop_Qt_6_7_2_MinGW_64_bit-Release","-IE:\\QT\\6.7.2\\mingw_64\\mkspecs\\win32-g++","-isystem","E:\\QT\\Tools\\mingw1120_64\\lib\\gcc\\x86_64-w64-mingw32\\11.2.0\\include\\c++","-isystem","E:\\QT\\Tools\\mingw1120_64\\lib\\gcc\\x86_64-w64-mingw32\\11.2.0\\include\\c++\\x86_64-w64-mingw32","-isystem","E:\\QT\\Tools\\mingw1120_64\\lib\\gcc\\x86_64-w64-mingw32\\11.2.0\\include\\c++\\backward","-isystem","E:\\QT\\Tools\\QtCreator\\bin\\clang\\lib\\clang\\17\\include","-isystem","E:\\QT\\Tools\\mingw1120_64\\x86_64-w64-mingw32\\include","-fmessage-length=0","-fdiagnostics-show-note-include-stack","-fretain-comments-from-system-headers","-fmacro-backtrace-limit=0","-ferror-limit=1000","-x","c++-header","D:\\SkullKing_Game\\SkullKing\\history.h"],"directory":"D:/SkullKing_Game/SkullKing/build/Desktop_Qt_6_7_2_MinGW_64_bit-Release/.qtc_clangd","file":"D:/SkullKing_Game/SkullKing/history.h"},{"arguments":["clang","-Wno-documentation-unknown-command","-Wno-unknown-warning-option","-Wno-unknown-pragmas","-nostdinc","-nostdinc++","-std=gnu++1z","-Wall","-Wextra","-Wextra","-fexceptions","-mthreads","-fsyntax-only","-m64","--target=x86_64-w64-mingw32","-DUNICODE","-D_UNICODE","-DWIN32","-DMINGW_HAS_SECURE_API","-DQT_NO_DEBUG","-DQT_WIDGETS_LIB","-DQT_GUI_LIB","-DQT_NETWORK_LIB","-DQT_CORE_LIB","-DQT_NEEDS_QMAIN","-DQ_CREATOR_RUN","-DQT_ANNOTATE_FUNCTION(x)=__attribute__((annotate(#x)))","-IE:\\QT\\Tools\\QtCreator\\share\\qtcreator\\cplusplus\\wrappedMingwHeaders","-IE:\\QT\\Tools\\QtCreator\\share\\qtcreator\\cplusplus\\wrappedQtHeaders","-IE:\\QT\\Tools\\QtCreator\\share\\qtcreator\\cplusplus\\wrappedQtHeaders\\QtCore","-ID:\\SkullKing_Game\\SkullKing","-IE:\\QT\\6.7.2\\mingw_64\\include","-IE:\\QT\\6.7.2\\mingw_64\\include\\QtWidgets","-IE:\\QT\\6.7.2\\mingw_64\\include\\QtGui","-IE:\\QT\\6.7.2\\mingw_64\\include\\QtNetwork","-IE:\\QT\\6.7.2\\mingw_64\\include\\QtCore","-ID:\\SkullKing_Game\\SkullKing\\build\\Desktop_Qt_6_7_2_MinGW_64_bit-Release\\release","-ID:\\SkullKing_Game\\SkullKing\\build\\Desktop_Qt_6_7_2_MinGW_64_bit-Release","-IE:\\QT\\6.7.2\\mingw_64\\mkspecs\\win32-g++","-isystem","E:\\QT\\Tools\\mingw1120_64\\lib\\gcc\\x86_64-w64-mingw32\\11.2.0\\include\\c++","-isystem","E:\\QT\\Tools\\mingw1120_64\\lib\\gcc\\x86_64-w64-mingw32\\11.2.0\\include\\c++\\x86_64-w64-mingw32","-isystem","E:\\QT\\Tools\\mingw1120_64\\lib\\gcc\\x86_64-w64-mingw32\\11.2.0\\include\\c++\\backward","-isystem","E:\\QT\\Tools\\QtCreator\\bin\\clang\\lib\\clang\\17\\include","-isystem","E:\\QT\\Tools\\mingw1120_64\\x86_64-w64-mingw32\\include","-fmessage-length=0","-fdiagnostics-show-note-include-stack","-fretain-comments-from-system-headers","-fmacro-backtrace-limit=0","-ferror-limit=1000","-x","c++-header","D:\\SkullKing_Game\\SkullKing\\importantcards.h"],"directory":"D:/SkullKing_Game/SkullKing/build/Desktop_Qt_6_7_2_MinGW_64_bit-Release/.qtc_clangd","file":"D:/SkullKing_Game/SkullKing/importantcards.h"},{"arguments":["clang","-Wno-documentation-unknown-command","-Wno-unknown-warning-option","-Wno-unknown-pragmas","-nostdinc","-nostdinc++","-std=gnu++1z","-Wall","-Wextra","-Wextra","-fexceptions","-mthreads","-fsyntax-only","-m64","--target=x86_64-w64-mingw32","-DUNICODE","-D_UNICODE","-DWIN32","-DMINGW_HAS_SECURE_API","-DQT_NO_DEBUG","-DQT_WIDGETS_LIB","-DQT_GUI_LIB","-DQT_NETWORK_LIB","-DQT_CORE_LIB","-DQT_NEEDS_QMAIN","-DQ_CREATOR_RUN","-DQT_ANNOTATE_FUNCTION(x)=__attribute__((annotate(#x)))","-IE:\\QT\\Tools\\QtCreator\\share\\qtcreator\\cplusplus\\wrappedMingwHeaders","-IE:\\QT\\Tools\\QtCreator\\share\\qtcreator\\cplusplus\\wrappedQtHeaders","-IE:\\QT\\Tools\\QtCreator\\share\\qtcreator\\cplusplus\\wrappedQtHeaders\\QtCore","-ID:\\SkullKing_Game\\SkullKing","-IE:\\QT\\6.7.2\\mingw_64\\include","-IE:\\QT\\6.7.2\\mingw_64\\include\\QtWidgets","-IE:\\QT\\6.7.2\\mingw_64\\include\\QtGui","-IE:\\QT\\6.7.2\\mingw_64\\include\\QtNetwork","-IE:\\QT\\6.7.2\\mingw_64\\include\\QtCore","-ID:\\SkullKing_Game\\SkullKing\\build\\Desktop_Qt_6_7_2_MinGW_64_bit-Release\\release","-ID:\\SkullKing_Game\\SkullKing\\build\\Desktop_Qt_6_7_2_MinGW_64_bit-Release","-IE:\\QT\\6.7.2\\mingw_64\\mkspecs\\win32-g++","-isystem","E:\\QT\\Tools\\mingw1120_64\\lib\\gcc\\x86_64-w64-mingw32\\11.2.0\\include\\c++","-isystem","E:\\QT\\Tools\\mingw1120_64\\lib\\gcc\\x86_64-w64-mingw32\\11.2.0\\include\\c++\\x86_64-w64-mingw32","-isystem","E:\\QT\\Tools\\mingw1120_64\\lib\\gcc\\x86_64-w64-mingw32\\11.2.0\\include\\c++\\backward","-isystem","E:\\QT\\Tools\\QtCreator\\bin\\clang\\lib\\clang\\17\\include","-isystem","E:\\QT\\Tools\\mingw1120_64\\x86_64-w64-mingw32\\include","-fmessage-length=0","-fdiagnostics-show-note-include-stack","-fretain-comments-from-system-headers","-fmacro-backtrace-limit=0","-ferror-limit=1000","-x","c++-header","D:\\SkullKing_Game\\SkullKing\\menu.h"],"directory":"D:/SkullKing_Game/SkullKing/build/Desktop_Qt_6_7_2_MinGW_64_bit-Release/.qtc_clangd","file":"D:/SkullKing_Game/SkullKing/menu.h"},{"arguments":["clang","-Wno-documentation-unknown-command","-Wno-unknown-warning-option","-Wno-unknown-pragmas","-nostdinc","-nostdinc++","-std=gnu++1z","-Wall","-Wextra","-Wextra","-fexceptions","-mthreads","-fsyntax-only","-m64","--target=x86_64-w64-mingw32","-DUNICODE","-D_UNICODE","-DWIN32","-DMINGW_HAS_SECURE_API","-DQT_NO_DEBUG","-DQT_WIDGETS_LIB","-DQT_GUI_LIB","-DQT_NETWORK_LIB","-DQT_CORE_LIB","-DQT_NEEDS_QMAIN","-DQ_CREATOR_RUN","-DQT_ANNOTATE_FUNCTION(x)=__attribute__((annotate(#x)))","-IE:\\QT\\Tools\\QtCreator\\share\\qtcreator\\cplusplus\\wrappedMingwHeaders","-IE:\\QT\\Tools\\QtCreator\\share\\qtcreator\\cplusplus\\wrappedQtHeaders","-IE:\\QT\\Tools\\QtCreator\\share\\qtcreator\\cplusplus\\wrappedQtHeaders\\QtCore","-ID:\\SkullKing_Game\\SkullKing","-IE:\\QT\\6.7.2\\mingw_64\\include","-IE:\\QT\\6.7.2\\mingw_64\\include\\QtWidgets","-IE:\\QT\\6.7.2\\mingw_64\\include\\QtGui","-IE:\\QT\\6.7.2\\mingw_64\\include\\QtNetwork","-IE:\\QT\\6.7.2\\mingw_64\\include\\QtCore","-ID:\\SkullKing_Game\\SkullKing\\build\\Desktop_Qt_6_7_2_MinGW_64_bit-Release\\release","-ID:\\SkullKing_Game\\SkullKing\\build\\Desktop_Qt_6_7_2_MinGW_64_bit-Release","-IE:\\QT\\6.7.2\\mingw_64\\mkspecs\\win32-g++","-isystem","E:\\QT\\Tools\\mingw1120_64\\lib\\gcc\\x86_64-w64-mingw32\\11.2.0\\include\\c++","-isystem","E:\\QT\\Tools\\mingw1120_64\\lib\\gcc\\x86_64-w64-mingw32\\11.2.0\\include\\c++\\x86_64-w64-mingw32","-isystem","E:\\QT\\Tools\\mingw1120_64\\lib\\gcc\\x86_64-w64-mingw32\\11.2.0\\include\\c++\\backward","-isystem","E:\\QT\\Tools\\QtCreator\\bin\\clang\\lib\\clang\\17\\include","-isystem","E:\\QT\\Tools\\mingw1120_64\\x86_64-w64-mingw32\\include","-fmessage-length=0","-fdiagnostics-show-note-include-stack","-fretain-comments-from-system-headers","-fmacro-backtrace-limit=0","-ferror-limit=1000","-x","c++-header","D:\\SkullKing_Game\\SkullKing\\player.h"],"directory":"D:/SkullKing_Game/SkullKing/build/Desktop_Qt_6_7_2_MinGW_64_bit-Release/.qtc_clangd","file":"D:/SkullKing_Game/SkullKing/player.h"},{"arguments":["clang","-Wno-documentation-unknown-command","-Wno-unknown-warning-option","-Wno-unknown-pragmas","-nostdinc","-nostdinc++","-std=gnu++1z","-Wall","-Wextra","-Wextra","-fexceptions","-mthreads","-fsyntax-only","-m64","--target=x86_64-w64-mingw32","-DUNICODE","-D_UNICODE","-DWIN32","-DMINGW_HAS_SECURE_API","-DQT_NO_DEBUG","-DQT_WIDGETS_LIB","-DQT_GUI_LIB","-DQT_NETWORK_LIB","-DQT_CORE_LIB","-DQT_NEEDS_QMAIN","-DQ_CREATOR_RUN","-DQT_ANNOTATE_FUNCTION(x)=__attribute__((annotate(#x)))","-IE:\\QT\\Tools\\QtCreator\\share\\qtcreator\\cplusplus\\wrappedMingwHeaders","-IE:\\QT\\Tools\\QtCreator\\share\\qtcreator\\cplusplus\\wrappedQtHeaders","-IE:\\QT\\Tools\\QtCreator\\share\\qtcreator\\cplusplus\\wrappedQtHeaders\\QtCore","-ID:\\SkullKing_Game\\SkullKing","-IE:\\QT\\6.7.2\\mingw_64\\include","-IE:\\QT\\6.7.2\\mingw_64\\include\\QtWidgets","-IE:\\QT\\6.7.2\\mingw_64\\include\\QtGui","-IE:\\QT\\6.7.2\\mingw_64\\include\\QtNetwork","-IE:\\QT\\6.7.2\\mingw_64\\include\\QtCore","-ID:\\SkullKing_Game\\SkullKing\\build\\Desktop_Qt_6_7_2_MinGW_64_bit-Release\\release","-ID:\\SkullKing_Game\\SkullKing\\build\\Desktop_Qt_6_7_2_MinGW_64_bit-Release","-IE:\\QT\\6.7.2\\mingw_64\\mkspecs\\win32-g++","-isystem","E:\\QT\\Tools\\mingw1120_64\\lib\\gcc\\x86_64-w64-mingw32\\11.2.0\\include\\c++","-isystem","E:\\QT\\Tools\\mingw1120_64\\lib\\gcc\\x86_64-w64-mingw32\\11.2.0\\include\\c++\\x86_64-w64-mingw32","-isystem","E:\\QT\\Tools\\mingw1120_64\\lib\\gcc\\x86_64-w64-mingw32\\11.2.0\\include\\c++\\backward","-isystem","E:\\QT\\Tools\\QtCreator\\bin\\clang\\lib\\clang\\17\\include","-isystem","E:\\QT\\Tools\\mingw1120_64\\x86_64-w64-mingw32\\include","-fmessage-length=0","-fdiagnostics-show-note-include-stack","-fretain-comments-from-system-headers","-fmacro-backtrace-limit=0","-ferror-limit=1000","-x","c++-header","D:\\SkullKing_Game\\SkullKing\\server.h"],"directory":"D:/SkullKing_Game/SkullKing/build/Desktop_Qt_6_7_2_MinGW_64_bit-Release/.qtc_clangd","file":"D:/SkullKing_Game/SkullKing/server.h"},{"arguments":["clang","-Wno-documentation-unknown-command","-Wno-unknown-warning-option","-Wno-unknown-pragmas","-nostdinc","-nostdinc++","-std=gnu++1z","-Wall","-Wextra","-Wextra","-fexceptions","-mthreads","-fsyntax-only","-m64","--target=x86_64-w64-mingw32","-DUNICODE","-D_UNICODE","-DWIN32","-DMINGW_HAS_SECURE_API","-DQT_NO_DEBUG","-DQT_WIDGETS_LIB","-DQT_GUI_LIB","-DQT_NETWORK_LIB","-DQT_CORE_LIB","-DQT_NEEDS_QMAIN","-DQ_CREATOR_RUN","-DQT_ANNOTATE_FUNCTION(x)=__attribute__((annotate(#x)))","-IE:\\QT\\Tools\\QtCreator\\share\\qtcreator\\cplusplus\\wrappedMingwHeaders","-IE:\\QT\\Tools\\QtCreator\\share\\qtcreator\\cplusplus\\wrappedQtHeaders","-IE:\\QT\\Tools\\QtCreator\\share\\qtcreator\\cplusplus\\wrappedQtHeaders\\QtCore","-ID:\\SkullKing_Game\\SkullKing","-IE:\\QT\\6.7.2\\mingw_64\\include","-IE:\\QT\\6.7.2\\mingw_64\\include\\QtWidgets","-IE:\\QT\\6.7.2\\mingw_64\\include\\QtGui","-IE:\\QT\\6.7.2\\mingw_64\\include\\QtNetwork","-IE:\\QT\\6.7.2\\mingw_64\\include\\QtCore","-ID:\\SkullKing_Game\\SkullKing\\build\\Desktop_Qt_6_7_2_MinGW_64_bit-Release\\release","-ID:\\SkullKing_Game\\SkullKing\\build\\Desktop_Qt_6_7_2_MinGW_64_bit-Release","-IE:\\QT\\6.7.2\\mingw_64\\mkspecs\\win32-g++","-isystem","E:\\QT\\Tools\\mingw1120_64\\lib\\gcc\\x86_64-w64-mingw32\\11.2.0\\include\\c++","-isystem","E:\\QT\\Tools\\mingw1120_64\\lib\\gcc\\x86_64-w64-mingw32\\11.2.0\\include\\c++\\x86_64-w64-mingw32","-isystem","E:\\QT\\Tools\\mingw1120_64\\lib\\gcc\\x86_64-w64-mingw32\\11.2.0\\include\\c++\\backward","-isystem","E:\\QT\\Tools\\QtCreator\\bin\\clang\\lib\\clang\\17\\include","-isystem","E:\\QT\\Tools\\mingw1120_64\\x86_64-w64-mingw32\\include","-fmessage-length=0","-fdiagnostics-show-note-include-stack","-fretain-comments-from-system-headers","-fmacro-backtrace-limit=0","-ferror-limit=1000","-x","c++-header","D:\\SkullKing_Game\\SkullKing\\signin.h"],"directory":"D:/SkullKing_Game/SkullKing/build/Desktop_Qt_6_7_2_MinGW_64_bit-Release/.qtc_clangd","file":"D:/SkullKing_Game/SkullKing/signin.h"},{"arguments":["clang","-Wno-documentation-unknown-command","-Wno-unknown-warning-option","-Wno-unknown-pragmas","-nostdinc","-nostdinc++","-std=gnu++1z","-Wall","-Wextra","-Wextra","-fexceptions","-mthreads","-fsyntax-only","-m64","--target=x86_64-w64-mingw32","-DUNICODE","-D_UNICODE","-DWIN32","-DMINGW_HAS_SECURE_API","-DQT_NO_DEBUG","-DQT_WIDGETS_LIB","-DQT_GUI_LIB","-DQT_NETWORK_LIB","-DQT_CORE_LIB","-DQT_NEEDS_QMAIN","-DQ_CREATOR_RUN","-DQT_ANNOTATE_FUNCTION(x)=__attribute__((annotate(#x)))","-IE:\\QT\\Tools\\QtCreator\\share\\qtcreator\\cplusplus\\wrappedMingwHeaders","-IE:\\QT\\Tools\\QtCreator\\share\\qtcreator\\cplusplus\\wrappedQtHeaders","-IE:\\QT\\Tools\\QtCreator\\share\\qtcreator\\cplusplus\\wrappedQtHeaders\\QtCore","-ID:\\SkullKing_Game\\SkullKing","-IE:\\QT\\6.7.2\\mingw_64\\include","-IE:\\QT\\6.7.2\\mingw_64\\include\\QtWidgets","-IE:\\QT\\6.7.2\\mingw_64\\include\\QtGui","-IE:\\QT\\6.7.2\\mingw_64\\include\\QtNetwork","-IE:\\QT\\6.7.2\\mingw_64\\include\\QtCore","-ID:\\SkullKing_Game\\SkullKing\\build\\Desktop_Qt_6_7_2_MinGW_64_bit-Release\\release","-ID:\\SkullKing_Game\\SkullKing\\build\\Desktop_Qt_6_7_2_MinGW_64_bit-Release","-IE:\\QT\\6.7.2\\mingw_64\\mkspecs\\win32-g++","-isystem","E:\\QT\\Tools\\mingw1120_64\\lib\\gcc\\x86_64-w64-mingw32\\11.2.0\\include\\c++","-isystem","E:\\QT\\Tools\\mingw1120_64\\lib\\gcc\\x86_64-w64-mingw32\\11.2.0\\include\\c++\\x86_64-w64-mingw32","-isystem","E:\\QT\\Tools\\mingw1120_64\\lib\\gcc\\x86_64-w64-mingw32\\11.2.0\\include\\c++\\backward","-isystem","E:\\QT\\Tools\\QtCreator\\bin\\clang\\lib\\clang\\17\\include","-isystem","E:\\QT\\Tools\\mingw1120_64\\x86_64-w64-mingw32\\include","-fmessage-length=0","-fdiagnostics-show-note-include-stack","-fretain-comments-from-system-headers","-fmacro-backtrace-limit=0","-ferror-limit=1000","-x","c++-header","D:\\SkullKing_Game\\SkullKing\\signup.h"],"directory":"D:/SkullKing_Game/SkullKing/build/Desktop_Qt_6_7_2_MinGW_64_bit-Release/.qtc_clangd","file":"D:/SkullKing_Game/SkullKing/signup.h"},{"arguments":["clang","-Wno-documentation-unknown-command","-Wno-unknown-warning-option","-Wno-unknown-pragmas","-nostdinc","-nostdinc++","-std=gnu++1z","-Wall","-Wextra","-Wextra","-fexceptions","-mthreads","-fsyntax-only","-m64","--target=x86_64-w64-mingw32","-DUNICODE","-D_UNICODE","-DWIN32","-DMINGW_HAS_SECURE_API","-DQT_NO_DEBUG","-DQT_WIDGETS_LIB","-DQT_GUI_LIB","-DQT_NETWORK_LIB","-DQT_CORE_LIB","-DQT_NEEDS_QMAIN","-DQ_CREATOR_RUN","-DQT_ANNOTATE_FUNCTION(x)=__attribute__((annotate(#x)))","-IE:\\QT\\Tools\\QtCreator\\share\\qtcreator\\cplusplus\\wrappedMingwHeaders","-IE:\\QT\\Tools\\QtCreator\\share\\qtcreator\\cplusplus\\wrappedQtHeaders","-IE:\\QT\\Tools\\QtCreator\\share\\qtcreator\\cplusplus\\wrappedQtHeaders\\QtCore","-ID:\\SkullKing_Game\\SkullKing","-IE:\\QT\\6.7.2\\mingw_64\\include","-IE:\\QT\\6.7.2\\mingw_64\\include\\QtWidgets","-IE:\\QT\\6.7.2\\mingw_64\\include\\QtGui","-IE:\\QT\\6.7.2\\mingw_64\\include\\QtNetwork","-IE:\\QT\\6.7.2\\mingw_64\\include\\QtCore","-ID:\\SkullKing_Game\\SkullKing\\build\\Desktop_Qt_6_7_2_MinGW_64_bit-Release\\release","-ID:\\SkullKing_Game\\SkullKing\\build\\Desktop_Qt_6_7_2_MinGW_64_bit-Release","-IE:\\QT\\6.7.2\\mingw_64\\mkspecs\\win32-g++","-isystem","E:\\QT\\Tools\\mingw1120_64\\lib\\gcc\\x86_64-w64-mingw32\\11.2.0\\include\\c++","-isystem","E:\\QT\\Tools\\mingw1120_64\\lib\\gcc\\x86_64-w64-mingw32\\11.2.0\\include\\c++\\x86_64-w64-mingw32","-isystem","E:\\QT\\Tools\\mingw1120_64\\lib\\gcc\\x86_64-w64-mingw32\\11.2.0\\include\\c++\\backward","-isystem","E:\\QT\\Tools\\QtCreator\\bin\\clang\\lib\\clang\\17\\include","-isystem","E:\\QT\\Tools\\mingw1120_64\\x86_64-w64-mingw32\\include","-fmessage-length=0","-fdiagnostics-show-note-include-stack","-fretain-comments-from-system-headers","-fmacro-backtrace-limit=0","-ferror-limit=1000","-x","c++-header","D:\\SkullKing_Game\\SkullKing\\skullking.h"],"directory":"D:/SkullKing_Game/SkullKing/build/Desktop_Qt_6_7_2_MinGW_64_bit-Release/.qtc_clangd","file":"D:/SkullKing_Game/SkullKing/skullking.h"},{"arguments":["clang","-Wno-documentation-unknown-command","-Wno-unknown-warning-option","-Wno-unknown-pragmas","-nostdinc","-nostdinc++","-std=gnu++1z","-Wall","-Wextra","-Wextra","-fexceptions","-mthreads","-fsyntax-only","-m64","--target=x86_64-w64-mingw32","-DUNICODE","-D_UNICODE","-DWIN32","-DMINGW_HAS_SECURE_API","-DQT_NO_DEBUG","-DQT_WIDGETS_LIB","-DQT_GUI_LIB","-DQT_NETWORK_LIB","-DQT_CORE_LIB","-DQT_NEEDS_QMAIN","-DQ_CREATOR_RUN","-DQT_ANNOTATE_FUNCTION(x)=__attribute__((annotate(#x)))","-IE:\\QT\\Tools\\QtCreator\\share\\qtcreator\\cplusplus\\wrappedMingwHeaders","-IE:\\QT\\Tools\\QtCreator\\share\\qtcreator\\cplusplus\\wrappedQtHeaders","-IE:\\QT\\Tools\\QtCreator\\share\\qtcreator\\cplusplus\\wrappedQtHeaders\\QtCore","-ID:\\SkullKing_Game\\SkullKing","-IE:\\QT\\6.7.2\\mingw_64\\include","-IE:\\QT\\6.7.2\\mingw_64\\include\\QtWidgets","-IE:\\QT\\6.7.2\\mingw_64\\include\\QtGui","-IE:\\QT\\6.7.2\\mingw_64\\include\\QtNetwork","-IE:\\QT\\6.7.2\\mingw_64\\include\\QtCore","-ID:\\SkullKing_Game\\SkullKing\\build\\Desktop_Qt_6_7_2_MinGW_64_bit-Release\\release","-ID:\\SkullKing_Game\\SkullKing\\build\\Desktop_Qt_6_7_2_MinGW_64_bit-Release","-IE:\\QT\\6.7.2\\mingw_64\\mkspecs\\win32-g++","-isystem","E:\\QT\\Tools\\mingw1120_64\\lib\\gcc\\x86_64-w64-mingw32\\11.2.0\\include\\c++","-isystem","E:\\QT\\Tools\\mingw1120_64\\lib\\gcc\\x86_64-w64-mingw32\\11.2.0\\include\\c++\\x86_64-w64-mingw32","-isystem","E:\\QT\\Tools\\mingw1120_64\\lib\\gcc\\x86_64-w64-mingw32\\11.2.0\\include\\c++\\backward","-isystem","E:\\QT\\Tools\\QtCreator\\bin\\clang\\lib\\clang\\17\\include","-isystem","E:\\QT\\Tools\\mingw1120_64\\x86_64-w64-mingw32\\include","-fmessage-length=0","-fdiagnostics-show-note-include-stack","-fretain-comments-from-system-headers","-fmacro-backtrace-limit=0","-ferror-limit=1000","-x","c++-header","D:\\SkullKing_Game\\SkullKing\\build\\Desktop_Qt_6_7_2_MinGW_64_bit-Release\\ui_history.h"],"directory":"D:/SkullKing_Game/SkullKing/build/Desktop_Qt_6_7_2_MinGW_64_bit-Release/.qtc_clangd","file":"D:/SkullKing_Game/SkullKing/build/Desktop_Qt_6_7_2_MinGW_64_bit-Release/ui_history.h"},{"arguments":["clang","-Wno-documentation-unknown-command","-Wno-unknown-warning-option","-Wno-unknown-pragmas","-nostdinc","-nostdinc++","-std=gnu++1z","-Wall","-Wextra","-Wextra","-fexceptions","-mthreads","-fsyntax-only","-m64","--target=x86_64-w64-mingw32","-DUNICODE","-D_UNICODE","-DWIN32","-DMINGW_HAS_SECURE_API","-DQT_NO_DEBUG","-DQT_WIDGETS_LIB","-DQT_GUI_LIB","-DQT_NETWORK_LIB","-DQT_CORE_LIB","-DQT_NEEDS_QMAIN","-DQ_CREATOR_RUN","-DQT_ANNOTATE_FUNCTION(x)=__attribute__((annotate(#x)))","-IE:\\QT\\Tools\\QtCreator\\share\\qtcreator\\cplusplus\\wrappedMingwHeaders","-IE:\\QT\\Tools\\QtCreator\\share\\qtcreator\\cplusplus\\wrappedQtHeaders","-IE:\\QT\\Tools\\QtCreator\\share\\qtcreator\\cplusplus\\wrappedQtHeaders\\QtCore","-ID:\\SkullKing_Game\\SkullKing","-IE:\\QT\\6.7.2\\mingw_64\\include","-IE:\\QT\\6.7.2\\mingw_64\\include\\QtWidgets","-IE:\\QT\\6.7.2\\mingw_64\\include\\QtGui","-IE:\\QT\\6.7.2\\mingw_64\\include\\QtNetwork","-IE:\\QT\\6.7.2\\mingw_64\\include\\QtCore","-ID:\\SkullKing_Game\\SkullKing\\build\\Desktop_Qt_6_7_2_MinGW_64_bit-Release\\release","-ID:\\SkullKing_Game\\SkullKing\\build\\Desktop_Qt_6_7_2_MinGW_64_bit-Release","-IE:\\QT\\6.7.2\\mingw_64\\mkspecs\\win32-g++","-isystem","E:\\QT\\Tools\\mingw1120_64\\lib\\gcc\\x86_64-w64-mingw32\\11.2.0\\include\\c++","-isystem","E:\\QT\\Tools\\mingw1120_64\\lib\\gcc\\x86_64-w64-mingw32\\11.2.0\\include\\c++\\x86_64-w64-mingw32","-isystem","E:\\QT\\Tools\\mingw1120_64\\lib\\gcc\\x86_64-w64-mingw32\\11.2.0\\include\\c++\\backward","-isystem","E:\\QT\\Tools\\QtCreator\\bin\\clang\\lib\\clang\\17\\include","-isystem","E:\\QT\\Tools\\mingw1120_64\\x86_64-w64-mingw32\\include","-fmessage-length=0","-fdiagnostics-show-note-include-stack","-fretain-comments-from-system-headers","-fmacro-backtrace-limit=0","-ferror-limit=1000","-x","c++-header","D:\\SkullKing_Game\\SkullKing\\build\\Desktop_Qt_6_7_2_MinGW_64_bit-Release\\ui_skullking.h"],"directory":"D:/SkullKing_Game/SkullKing/build/Desktop_Qt_6_7_2_MinGW_64_bit-Release/.qtc_clangd","file":"D:/SkullKing_Game/SkullKing/build/Desktop_Qt_6_7_2_MinGW_64_bit-Release/ui_skullking.h"},{"arguments":["clang","-Wno-documentation-unknown-command","-Wno-unknown-warning-option","-Wno-unknown-pragmas","-nostdinc","-nostdinc++","-std=gnu++1z","-Wall","-Wextra","-Wextra","-fexceptions","-mthreads","-fsyntax-only","-m64","--target=x86_64-w64-mingw32","-DUNICODE","-D_UNICODE","-DWIN32","-DMINGW_HAS_SECURE_API","-DQT_NO_DEBUG","-DQT_WIDGETS_LIB","-DQT_GUI_LIB","-DQT_NETWORK_LIB","-DQT_CORE_LIB","-DQT_NEEDS_QMAIN","-DQ_CREATOR_RUN","-DQT_ANNOTATE_FUNCTION(x)=__attribute__((annotate(#x)))","-IE:\\QT\\Tools\\QtCreator\\share\\qtcreator\\cplusplus\\wrappedMingwHeaders","-IE:\\QT\\Tools\\QtCreator\\share\\qtcreator\\cplusplus\\wrappedQtHeaders","-IE:\\QT\\Tools\\QtCreator\\share\\qtcreator\\cplusplus\\wrappedQtHeaders\\QtCore","-ID:\\SkullKing_Game\\SkullKing","-IE:\\QT\\6.7.2\\mingw_64\\include","-IE:\\QT\\6.7.2\\mingw_64\\include\\QtWidgets","-IE:\\QT\\6.7.2\\mingw_64\\include\\QtGui","-IE:\\QT\\6.7.2\\mingw_64\\include\\QtNetwork","-IE:\\QT\\6.7.2\\mingw_64\\include\\QtCore","-ID:\\SkullKing_Game\\SkullKing\\build\\Desktop_Qt_6_7_2_MinGW_64_bit-Release\\release","-ID:\\SkullKing_Game\\SkullKing\\build\\Desktop_Qt_6_7_2_MinGW_64_bit-Release","-IE:\\QT\\6.7.2\\mingw_64\\mkspecs\\win32-g++","-isystem","E:\\QT\\Tools\\mingw1120_64\\lib\\gcc\\x86_64-w64-mingw32\\11.2.0\\include\\c++","-isystem","E:\\QT\\Tools\\mingw1120_64\\lib\\gcc\\x86_64-w64-mingw32\\11.2.0\\include\\c++\\x86_64-w64-mingw32","-isystem","E:\\QT\\Tools\\mingw1120_64\\lib\\gcc\\x86_64-w64-mingw32\\11.2.0\\include\\c++\\backward","-isystem","E:\\QT\\Tools\\QtCreator\\bin\\clang\\lib\\clang\\17\\include","-isystem","E:\\QT\\Tools\\mingw1120_64\\x86_64-w64-mingw32\\include","-fmessage-length=0","-fdiagnostics-show-note-include-stack","-fretain-comments-from-system-headers","-fmacro-backtrace-limit=0","-ferror-limit=1000","-x","c++-header","D:\\SkullKing_Game\\SkullKing\\build\\Desktop_Qt_6_7_2_MinGW_64_bit-Release\\ui_changeinformation.h"],"directory":"D:/SkullKing_Game/SkullKing/build/Desktop_Qt_6_7_2_MinGW_64_bit-Release/.qtc_clangd","file":"D:/SkullKing_Game/SkullKing/build/Desktop_Qt_6_7_2_MinGW_64_bit-Release/ui_changeinformation.h"},{"arguments":["clang","-Wno-documentation-unknown-command","-Wno-unknown-warning-option","-Wno-unknown-pragmas","-nostdinc","-nostdinc++","-std=gnu++1z","-Wall","-Wextra","-Wextra","-fexceptions","-mthreads","-fsyntax-only","-m64","--target=x86_64-w64-mingw32","-DUNICODE","-D_UNICODE","-DWIN32","-DMINGW_HAS_SECURE_API","-DQT_NO_DEBUG","-DQT_WIDGETS_LIB","-DQT_GUI_LIB","-DQT_NETWORK_LIB","-DQT_CORE_LIB","-DQT_NEEDS_QMAIN","-DQ_CREATOR_RUN","-DQT_ANNOTATE_FUNCTION(x)=__attribute__((annotate(#x)))","-IE:\\QT\\Tools\\QtCreator\\share\\qtcreator\\cplusplus\\wrappedMingwHeaders","-IE:\\QT\\Tools\\QtCreator\\share\\qtcreator\\cplusplus\\wrappedQtHeaders","-IE:\\QT\\Tools\\QtCreator\\share\\qtcreator\\cplusplus\\wrappedQtHeaders\\QtCore","-ID:\\SkullKing_Game\\SkullKing","-IE:\\QT\\6.7.2\\mingw_64\\include","-IE:\\QT\\6.7.2\\mingw_64\\include\\QtWidgets","-IE:\\QT\\6.7.2\\mingw_64\\include\\QtGui","-IE:\\QT\\6.7.2\\mingw_64\\include\\QtNetwork","-IE:\\QT\\6.7.2\\mingw_64\\include\\QtCore","-ID:\\SkullKing_Game\\SkullKing\\build\\Desktop_Qt_6_7_2_MinGW_64_bit-Release\\release","-ID:\\SkullKing_Game\\SkullKing\\build\\Desktop_Qt_6_7_2_MinGW_64_bit-Release","-IE:\\QT\\6.7.2\\mingw_64\\mkspecs\\win32-g++","-isystem","E:\\QT\\Tools\\mingw1120_64\\lib\\gcc\\x86_64-w64-mingw32\\11.2.0\\include\\c++","-isystem","E:\\QT\\Tools\\mingw1120_64\\lib\\gcc\\x86_64-w64-mingw32\\11.2.0\\include\\c++\\x86_64-w64-mingw32","-isystem","E:\\QT\\Tools\\mingw1120_64\\lib\\gcc\\x86_64-w64-mingw32\\11.2.0\\include\\c++\\backward","-isystem","E:\\QT\\Tools\\QtCreator\\bin\\clang\\lib\\clang\\17\\include","-isystem","E:\\QT\\Tools\\mingw1120_64\\x86_64-w64-mingw32\\include","-fmessage-length=0","-fdiagnostics-show-note-include-stack","-fretain-comments-from-system-headers","-fmacro-backtrace-limit=0","-ferror-limit=1000","-x","c++-header","D:\\SkullKing_Game\\SkullKing\\build\\Desktop_Qt_6_7_2_MinGW_64_bit-Release\\ui_clientorserver.h"],"directory":"D:/SkullKing_Game/SkullKing/build/Desktop_Qt_6_7_2_MinGW_64_bit-Release/.qtc_clangd","file":"D:/SkullKing_Game/SkullKing/build/Desktop_Qt_6_7_2_MinGW_64_bit-Release/ui_clientorserver.h"},{"arguments":["clang","-Wno-documentation-unknown-command","-Wno-unknown-warning-option","-Wno-unknown-pragmas","-nostdinc","-nostdinc++","-std=gnu++1z","-Wall","-Wextra","-Wextra","-fexceptions","-mthreads","-fsyntax-only","-m64","--target=x86_64-w64-mingw32","-DUNICODE","-D_UNICODE","-DWIN32","-DMINGW_HAS_SECURE_API","-DQT_NO_DEBUG","-DQT_WIDGETS_LIB","-DQT_GUI_LIB","-DQT_NETWORK_LIB","-DQT_CORE_LIB","-DQT_NEEDS_QMAIN","-DQ_CREATOR_RUN","-DQT_ANNOTATE_FUNCTION(x)=__attribute__((annotate(#x)))","-IE:\\QT\\Tools\\QtCreator\\share\\qtcreator\\cplusplus\\wrappedMingwHeaders","-IE:\\QT\\Tools\\QtCreator\\share\\qtcreator\\cplusplus\\wrappedQtHeaders","-IE:\\QT\\Tools\\QtCreator\\share\\qtcreator\\cplusplus\\wrappedQtHeaders\\QtCore","-ID:\\SkullKing_Game\\SkullKing","-IE:\\QT\\6.7.2\\mingw_64\\include","-IE:\\QT\\6.7.2\\mingw_64\\include\\QtWidgets","-IE:\\QT\\6.7.2\\mingw_64\\include\\QtGui","-IE:\\QT\\6.7.2\\mingw_64\\include\\QtNetwork","-IE:\\QT\\6.7.2\\mingw_64\\include\\QtCore","-ID:\\SkullKing_Game\\SkullKing\\build\\Desktop_Qt_6_7_2_MinGW_64_bit-Release\\release","-ID:\\SkullKing_Game\\SkullKing\\build\\Desktop_Qt_6_7_2_MinGW_64_bit-Release","-IE:\\QT\\6.7.2\\mingw_64\\mkspecs\\win32-g++","-isystem","E:\\QT\\Tools\\mingw1120_64\\lib\\gcc\\x86_64-w64-mingw32\\11.2.0\\include\\c++","-isystem","E:\\QT\\Tools\\mingw1120_64\\lib\\gcc\\x86_64-w64-mingw32\\11.2.0\\include\\c++\\x86_64-w64-mingw32","-isystem","E:\\QT\\Tools\\mingw1120_64\\lib\\gcc\\x86_64-w64-mingw32\\11.2.0\\include\\c++\\backward","-isystem","E:\\QT\\Tools\\QtCreator\\bin\\clang\\lib\\clang\\17\\include","-isystem","E:\\QT\\Tools\\mingw1120_64\\x86_64-w64-mingw32\\include","-fmessage-length=0","-fdiagnostics-show-note-include-stack","-fretain-comments-from-system-headers","-fmacro-backtrace-limit=0","-ferror-limit=1000","-x","c++-header","D:\\SkullKing_Game\\SkullKing\\build\\Desktop_Qt_6_7_2_MinGW_64_bit-Release\\ui_forgetpassword.h"],"directory":"D:/SkullKing_Game/SkullKing/build/Desktop_Qt_6_7_2_MinGW_64_bit-Release/.qtc_clangd","file":"D:/SkullKing_Game/SkullKing/build/Desktop_Qt_6_7_2_MinGW_64_bit-Release/ui_forgetpassword.h"},{"arguments":["clang","-Wno-documentation-unknown-command","-Wno-unknown-warning-option","-Wno-unknown-pragmas","-nostdinc","-nostdinc++","-std=gnu++1z","-Wall","-Wextra","-Wextra","-fexceptions","-mthreads","-fsyntax-only","-m64","--target=x86_64-w64-mingw32","-DUNICODE","-D_UNICODE","-DWIN32","-DMINGW_HAS_SECURE_API","-DQT_NO_DEBUG","-DQT_WIDGETS_LIB","-DQT_GUI_LIB","-DQT_NETWORK_LIB","-DQT_CORE_LIB","-DQT_NEEDS_QMAIN","-DQ_CREATOR_RUN","-DQT_ANNOTATE_FUNCTION(x)=__attribute__((annotate(#x)))","-IE:\\QT\\Tools\\QtCreator\\share\\qtcreator\\cplusplus\\wrappedMingwHeaders","-IE:\\QT\\Tools\\QtCreator\\share\\qtcreator\\cplusplus\\wrappedQtHeaders","-IE:\\QT\\Tools\\QtCreator\\share\\qtcreator\\cplusplus\\wrappedQtHeaders\\QtCore","-ID:\\SkullKing_Game\\SkullKing","-IE:\\QT\\6.7.2\\mingw_64\\include","-IE:\\QT\\6.7.2\\mingw_64\\include\\QtWidgets","-IE:\\QT\\6.7.2\\mingw_64\\include\\QtGui","-IE:\\QT\\6.7.2\\mingw_64\\include\\QtNetwork","-IE:\\QT\\6.7.2\\mingw_64\\include\\QtCore","-ID:\\SkullKing_Game\\SkullKing\\build\\Desktop_Qt_6_7_2_MinGW_64_bit-Release\\release","-ID:\\SkullKing_Game\\SkullKing\\build\\Desktop_Qt_6_7_2_MinGW_64_bit-Release","-IE:\\QT\\6.7.2\\mingw_64\\mkspecs\\win32-g++","-isystem","E:\\QT\\Tools\\mingw1120_64\\lib\\gcc\\x86_64-w64-mingw32\\11.2.0\\include\\c++","-isystem","E:\\QT\\Tools\\mingw1120_64\\lib\\gcc\\x86_64-w64-mingw32\\11.2.0\\include\\c++\\x86_64-w64-mingw32","-isystem","E:\\QT\\Tools\\mingw1120_64\\lib\\gcc\\x86_64-w64-mingw32\\11.2.0\\include\\c++\\backward","-isystem","E:\\QT\\Tools\\QtCreator\\bin\\clang\\lib\\clang\\17\\include","-isystem","E:\\QT\\Tools\\mingw1120_64\\x86_64-w64-mingw32\\include","-fmessage-length=0","-fdiagnostics-show-note-include-stack","-fretain-comments-from-system-headers","-fmacro-backtrace-limit=0","-ferror-limit=1000","-x","c++-header","D:\\SkullKing_Game\\SkullKing\\build\\Desktop_Qt_6_7_2_MinGW_64_bit-Release\\ui_signup.h"],"directory":"D:/SkullKing_Game/SkullKing/build/Desktop_Qt_6_7_2_MinGW_64_bit-Release/.qtc_clangd","file":"D:/SkullKing_Game/SkullKing/build/Desktop_Qt_6_7_2_MinGW_64_bit-Release/ui_signup.h"},{"arguments":["clang","-Wno-documentation-unknown-command","-Wno-unknown-warning-option","-Wno-unknown-pragmas","-nostdinc","-nostdinc++","-std=gnu++1z","-Wall","-Wextra","-Wextra","-fexceptions","-mthreads","-fsyntax-only","-m64","--target=x86_64-w64-mingw32","-DUNICODE","-D_UNICODE","-DWIN32","-DMINGW_HAS_SECURE_API","-DQT_NO_DEBUG","-DQT_WIDGETS_LIB","-DQT_GUI_LIB","-DQT_NETWORK_LIB","-DQT_CORE_LIB","-DQT_NEEDS_QMAIN","-DQ_CREATOR_RUN","-DQT_ANNOTATE_FUNCTION(x)=__attribute__((annotate(#x)))","-IE:\\QT\\Tools\\QtCreator\\share\\qtcreator\\cplusplus\\wrappedMingwHeaders","-IE:\\QT\\Tools\\QtCreator\\share\\qtcreator\\cplusplus\\wrappedQtHeaders","-IE:\\QT\\Tools\\QtCreator\\share\\qtcreator\\cplusplus\\wrappedQtHeaders\\QtCore","-ID:\\SkullKing_Game\\SkullKing","-IE:\\QT\\6.7.2\\mingw_64\\include","-IE:\\QT\\6.7.2\\mingw_64\\include\\QtWidgets","-IE:\\QT\\6.7.2\\mingw_64\\include\\QtGui","-IE:\\QT\\6.7.2\\mingw_64\\include\\QtNetwork","-IE:\\QT\\6.7.2\\mingw_64\\include\\QtCore","-ID:\\SkullKing_Game\\SkullKing\\build\\Desktop_Qt_6_7_2_MinGW_64_bit-Release\\release","-ID:\\SkullKing_Game\\SkullKing\\build\\Desktop_Qt_6_7_2_MinGW_64_bit-Release","-IE:\\QT\\6.7.2\\mingw_64\\mkspecs\\win32-g++","-isystem","E:\\QT\\Tools\\mingw1120_64\\lib\\gcc\\x86_64-w64-mingw32\\11.2.0\\include\\c++","-isystem","E:\\QT\\Tools\\mingw1120_64\\lib\\gcc\\x86_64-w64-mingw32\\11.2.0\\include\\c++\\x86_64-w64-mingw32","-isystem","E:\\QT\\Tools\\mingw1120_64\\lib\\gcc\\x86_64-w64-mingw32\\11.2.0\\include\\c++\\backward","-isystem","E:\\QT\\Tools\\QtCreator\\bin\\clang\\lib\\clang\\17\\include","-isystem","E:\\QT\\Tools\\mingw1120_64\\x86_64-w64-mingw32\\include","-fmessage-length=0","-fdiagnostics-show-note-include-stack","-fretain-comments-from-system-headers","-fmacro-backtrace-limit=0","-ferror-limit=1000","-x","c++-header","D:\\SkullKing_Game\\SkullKing\\build\\Desktop_Qt_6_7_2_MinGW_64_bit-Release\\ui_server.h"],"directory":"D:/SkullKing_Game/SkullKing/build/Desktop_Qt_6_7_2_MinGW_64_bit-Release/.qtc_clangd","file":"D:/SkullKing_Game/SkullKing/build/Desktop_Qt_6_7_2_MinGW_64_bit-Release/ui_server.h"},{"arguments":["clang","-Wno-documentation-unknown-command","-Wno-unknown-warning-option","-Wno-unknown-pragmas","-nostdinc","-nostdinc++","-std=gnu++1z","-Wall","-Wextra","-Wextra","-fexceptions","-mthreads","-fsyntax-only","-m64","--target=x86_64-w64-mingw32","-DUNICODE","-D_UNICODE","-DWIN32","-DMINGW_HAS_SECURE_API","-DQT_NO_DEBUG","-DQT_WIDGETS_LIB","-DQT_GUI_LIB","-DQT_NETWORK_LIB","-DQT_CORE_LIB","-DQT_NEEDS_QMAIN","-DQ_CREATOR_RUN","-DQT_ANNOTATE_FUNCTION(x)=__attribute__((annotate(#x)))","-IE:\\QT\\Tools\\QtCreator\\share\\qtcreator\\cplusplus\\wrappedMingwHeaders","-IE:\\QT\\Tools\\QtCreator\\share\\qtcreator\\cplusplus\\wrappedQtHeaders","-IE:\\QT\\Tools\\QtCreator\\share\\qtcreator\\cplusplus\\wrappedQtHeaders\\QtCore","-ID:\\SkullKing_Game\\SkullKing","-IE:\\QT\\6.7.2\\mingw_64\\include","-IE:\\QT\\6.7.2\\mingw_64\\include\\QtWidgets","-IE:\\QT\\6.7.2\\mingw_64\\include\\QtGui","-IE:\\QT\\6.7.2\\mingw_64\\include\\QtNetwork","-IE:\\QT\\6.7.2\\mingw_64\\include\\QtCore","-ID:\\SkullKing_Game\\SkullKing\\build\\Desktop_Qt_6_7_2_MinGW_64_bit-Release\\release","-ID:\\SkullKing_Game\\SkullKing\\build\\Desktop_Qt_6_7_2_MinGW_64_bit-Release","-IE:\\QT\\6.7.2\\mingw_64\\mkspecs\\win32-g++","-isystem","E:\\QT\\Tools\\mingw1120_64\\lib\\gcc\\x86_64-w64-mingw32\\11.2.0\\include\\c++","-isystem","E:\\QT\\Tools\\mingw1120_64\\lib\\gcc\\x86_64-w64-mingw32\\11.2.0\\include\\c++\\x86_64-w64-mingw32","-isystem","E:\\QT\\Tools\\mingw1120_64\\lib\\gcc\\x86_64-w64-mingw32\\11.2.0\\include\\c++\\backward","-isystem","E:\\QT\\Tools\\QtCreator\\bin\\clang\\lib\\clang\\17\\include","-isystem","E:\\QT\\Tools\\mingw1120_64\\x86_64-w64-mingw32\\include","-fmessage-length=0","-fdiagnostics-show-note-include-stack","-fretain-comments-from-system-headers","-fmacro-backtrace-limit=0","-ferror-limit=1000","-x","c++-header","D:\\SkullKing_Game\\SkullKing\\build\\Desktop_Qt_6_7_2_MinGW_64_bit-Release\\ui_client.h"],"directory":"D:/SkullKing_Game/SkullKing/build/Desktop_Qt_6_7_2_MinGW_64_bit-Release/.qtc_clangd","file":"D:/SkullKing_Game/SkullKing/build/Desktop_Qt_6_7_2_MinGW_64_bit-Release/ui_client.h"},{"arguments":["clang","-Wno-documentation-unknown-command","-Wno-unknown-warning-option","-Wno-unknown-pragmas","-nostdinc","-nostdinc++","-std=gnu++1z","-Wall","-Wextra","-Wextra","-fexceptions","-mthreads","-fsyntax-only","-m64","--target=x86_64-w64-mingw32","-DUNICODE","-D_UNICODE","-DWIN32","-DMINGW_HAS_SECURE_API","-DQT_NO_DEBUG","-DQT_WIDGETS_LIB","-DQT_GUI_LIB","-DQT_NETWORK_LIB","-DQT_CORE_LIB","-DQT_NEEDS_QMAIN","-DQ_CREATOR_RUN","-DQT_ANNOTATE_FUNCTION(x)=__attribute__((annotate(#x)))","-IE:\\QT\\Tools\\QtCreator\\share\\qtcreator\\cplusplus\\wrappedMingwHeaders","-IE:\\QT\\Tools\\QtCreator\\share\\qtcreator\\cplusplus\\wrappedQtHeaders","-IE:\\QT\\Tools\\QtCreator\\share\\qtcreator\\cplusplus\\wrappedQtHeaders\\QtCore","-ID:\\SkullKing_Game\\SkullKing","-IE:\\QT\\6.7.2\\mingw_64\\include","-IE:\\QT\\6.7.2\\mingw_64\\include\\QtWidgets","-IE:\\QT\\6.7.2\\mingw_64\\include\\QtGui","-IE:\\QT\\6.7.2\\mingw_64\\include\\QtNetwork","-IE:\\QT\\6.7.2\\mingw_64\\include\\QtCore","-ID:\\SkullKing_Game\\SkullKing\\build\\Desktop_Qt_6_7_2_MinGW_64_bit-Release\\release","-ID:\\SkullKing_Game\\SkullKing\\build\\Desktop_Qt_6_7_2_MinGW_64_bit-Release","-IE:\\QT\\6.7.2\\mingw_64\\mkspecs\\win32-g++","-isystem","E:\\QT\\Tools\\mingw1120_64\\lib\\gcc\\x86_64-w64-mingw32\\11.2.0\\include\\c++","-isystem","E:\\QT\\Tools\\mingw1120_64\\lib\\gcc\\x86_64-w64-mingw32\\11.2.0\\include\\c++\\x86_64-w64-mingw32","-isystem","E:\\QT\\Tools\\mingw1120_64\\lib\\gcc\\x86_64-w64-mingw32\\11.2.0\\include\\c++\\backward","-isystem","E:\\QT\\Tools\\QtCreator\\bin\\clang\\lib\\clang\\17\\include","-isystem","E:\\QT\\Tools\\mingw1120_64\\x86_64-w64-mingw32\\include","-fmessage-length=0","-fdiagnostics-show-note-include-stack","-fretain-comments-from-system-headers","-fmacro-backtrace-limit=0","-ferror-limit=1000","-x","c++-header","D:\\SkullKing_Game\\SkullKing\\build\\Desktop_Qt_6_7_2_MinGW_64_bit-Release\\ui_menu.h"],"directory":"D:/SkullKing_Game/SkullKing/build/Desktop_Qt_6_7_2_MinGW_64_bit-Release/.qtc_clangd","file":"D:/SkullKing_Game/SkullKing/build/Desktop_Qt_6_7_2_MinGW_64_bit-Release/ui_menu.h"},{"arguments":["clang","-Wno-documentation-unknown-command","-Wno-unknown-warning-option","-Wno-unknown-pragmas","-nostdinc","-nostdinc++","-std=gnu++1z","-Wall","-Wextra","-Wextra","-fexceptions","-mthreads","-fsyntax-only","-m64","--target=x86_64-w64-mingw32","-DUNICODE","-D_UNICODE","-DWIN32","-DMINGW_HAS_SECURE_API","-DQT_NO_DEBUG","-DQT_WIDGETS_LIB","-DQT_GUI_LIB","-DQT_NETWORK_LIB","-DQT_CORE_LIB","-DQT_NEEDS_QMAIN","-DQ_CREATOR_RUN","-DQT_ANNOTATE_FUNCTION(x)=__attribute__((annotate(#x)))","-IE:\\QT\\Tools\\QtCreator\\share\\qtcreator\\cplusplus\\wrappedMingwHeaders","-IE:\\QT\\Tools\\QtCreator\\share\\qtcreator\\cplusplus\\wrappedQtHeaders","-IE:\\QT\\Tools\\QtCreator\\share\\qtcreator\\cplusplus\\wrappedQtHeaders\\QtCore","-ID:\\SkullKing_Game\\SkullKing","-IE:\\QT\\6.7.2\\mingw_64\\include","-IE:\\QT\\6.7.2\\mingw_64\\include\\QtWidgets","-IE:\\QT\\6.7.2\\mingw_64\\include\\QtGui","-IE:\\QT\\6.7.2\\mingw_64\\include\\QtNetwork","-IE:\\QT\\6.7.2\\mingw_64\\include\\QtCore","-ID:\\SkullKing_Game\\SkullKing\\build\\Desktop_Qt_6_7_2_MinGW_64_bit-Release\\release","-ID:\\SkullKing_Game\\SkullKing\\build\\Desktop_Qt_6_7_2_MinGW_64_bit-Release","-IE:\\QT\\6.7.2\\mingw_64\\mkspecs\\win32-g++","-isystem","E:\\QT\\Tools\\mingw1120_64\\lib\\gcc\\x86_64-w64-mingw32\\11.2.0\\include\\c++","-isystem","E:\\QT\\Tools\\mingw1120_64\\lib\\gcc\\x86_64-w64-mingw32\\11.2.0\\include\\c++\\x86_64-w64-mingw32","-isystem","E:\\QT\\Tools\\mingw1120_64\\lib\\gcc\\x86_64-w64-mingw32\\11.2.0\\include\\c++\\backward","-isystem","E:\\QT\\Tools\\QtCreator\\bin\\clang\\lib\\clang\\17\\include","-isystem","E:\\QT\\Tools\\mingw1120_64\\x86_64-w64-mingw32\\include","-fmessage-length=0","-fdiagnostics-show-note-include-stack","-fretain-comments-from-system-headers","-fmacro-backtrace-limit=0","-ferror-limit=1000","-x","c++-header","D:\\SkullKing_Game\\SkullKing\\build\\Desktop_Qt_6_7_2_MinGW_64_bit-Release\\ui_signin.h"],"directory":"D:/SkullKing_Game/SkullKing/build/Desktop_Qt_6_7_2_MinGW_64_bit-Release/.qtc_clangd","file":"D:/SkullKing_Game/SkullKing/build/Desktop_Qt_6_7_2_MinGW_64_bit-Release/ui_signin.h"}]